[
{"Name": ["Adams, John"], "Link": "https://www.pgatour.com/players/players/player.01006.john-adams.html"},
{"Name": ["Adams, Sam"], "Link": "https://www.pgatour.com/players/players/player.01007.sam-adams.html"},
{"Name": ["Aguilar, Felipe"], "Link": "https://www.pgatour.com/players/players/player.23783.felipe-aguilar.html"},
{"Name": ["Albertson, Anders"], "Link": "https://www.pgatour.com/players/players/player.49303.anders-albertson.html"},
{"Name": ["Allem, Fulton"], "Link": "https://www.pgatour.com/players/players/player.01014.fulton-allem.html"},
{"Name": ["Allen, Michael"], "Link": "https://www.pgatour.com/players/players/player.06197.michael-allen.html"},
{"Name": ["Allenby, Robert"], "Link": "https://www.pgatour.com/players/players/player.10885.robert-allenby.html"},
{"Name": ["Ames, Stephen"], "Link": "https://www.pgatour.com/players/players/player.06004.stephen-ames.html"},
{"Name": ["An, Byeong Hun"], "Link": "https://www.pgatour.com/players/players/player.33948.byeong-hun-an.html"},
{"Name": ["Ancer, Abraham"], "Link": "https://www.pgatour.com/players/players/player.45526.abraham-ancer.html"},
{"Name": ["Andersson Hed, Fredrik"], "Link": "https://www.pgatour.com/players/players/player.20367.fredrik-andersson-hed.html"},
{"Name": ["Andrade, Billy"], "Link": "https://www.pgatour.com/players/players/player.01024.billy-andrade.html"},
{"Name": ["Aoki, Isao"], "Link": "https://www.pgatour.com/players/players/player.01030.isao-aoki.html"},
{"Name": ["Aphibarnrat, Kiradech"], "Link": "https://www.pgatour.com/players/players/player.30978.kiradech-aphibarnrat.html"},
{"Name": ["Appleby, Stuart"], "Link": "https://www.pgatour.com/players/players/player.20098.stuart-appleby.html"},
{"Name": ["Armour, Ryan"], "Link": "https://www.pgatour.com/players/players/player.19803.ryan-armour.html"},
{"Name": ["Armour III, Tommy"], "Link": "https://www.pgatour.com/players/players/player.01035.tommy-armour-iii.html"},
{"Name": ["Armstrong, Wally"], "Link": "https://www.pgatour.com/players/players/player.01036.wally-armstrong.html"},
{"Name": ["Atwal, Arjun"], "Link": "https://www.pgatour.com/players/players/player.21407.arjun-atwal.html"},
{"Name": ["Austin, Woody"], "Link": "https://www.pgatour.com/players/players/player.07867.woody-austin.html"},
{"Name": ["Axley, Eric"], "Link": "https://www.pgatour.com/players/players/player.23048.eric-axley.html"},
{"Name": ["Azinger, Paul"], "Link": "https://www.pgatour.com/players/players/player.01042.paul-azinger.html"},
{"Name": ["Baddeley, Aaron"], "Link": "https://www.pgatour.com/players/players/player.22371.aaron-baddeley.html"},
{"Name": ["Bae, Sangmoon"], "Link": "https://www.pgatour.com/players/players/player.28259.sangmoon-bae.html"},
{"Name": ["Baird, Briny"], "Link": "https://www.pgatour.com/players/players/player.20498.briny-baird.html"},
{"Name": ["Baker-Finch, Ian"], "Link": "https://www.pgatour.com/players/players/player.01049.ian-baker-finch.html"},
{"Name": ["Barlow, Craig"], "Link": "https://www.pgatour.com/players/players/player.19824.craig-barlow.html"},
{"Name": ["Barnes, Ricky"], "Link": "https://www.pgatour.com/players/players/player.24846.ricky-barnes.html"},
{"Name": ["Barr, Dave"], "Link": "https://www.pgatour.com/players/players/player.01060.dave-barr.html"},
{"Name": ["Bateman, Brian"], "Link": "https://www.pgatour.com/players/players/player.07223.brian-bateman.html"},
{"Name": ["Bean, Andy"], "Link": "https://www.pgatour.com/players/players/player.01068.andy-bean.html"},
{"Name": ["Beck, Chip"], "Link": "https://www.pgatour.com/players/players/player.01072.chip-beck.html"},
{"Name": ["Beckman, Cameron"], "Link": "https://www.pgatour.com/players/players/player.12652.cameron-beckman.html"},
{"Name": ["Beem, Rich"], "Link": "https://www.pgatour.com/players/players/player.23614.rich-beem.html"},
{"Name": ["Begay III, Notah"], "Link": "https://www.pgatour.com/players/players/player.20029.notah-begay-iii.html"},
{"Name": ["Beljan, Charlie"], "Link": "https://www.pgatour.com/players/players/player.32334.charlie-beljan.html"},
{"Name": ["Beman, Deane"], "Link": "https://www.pgatour.com/players/players/player.01076.deane-beman.html"},
{"Name": ["Benepe, Jim"], "Link": "https://www.pgatour.com/players/players/player.01078.jim-benepe.html"},
{"Name": ["Berganio, Jr., David"], "Link": "https://www.pgatour.com/players/players/player.07003.david-berganio--jr-.html"},
{"Name": ["Berger, Daniel"], "Link": "https://www.pgatour.com/players/players/player.40026.daniel-berger.html"},
{"Name": ["Besselink, Al"], "Link": "https://www.pgatour.com/players/players/player.01084.al-besselink.html"},
{"Name": ["Bettencourt, Matt"], "Link": "https://www.pgatour.com/players/players/player.20070.matt-bettencourt.html"},
{"Name": ["Bhullar, Gaganjeet"], "Link": "https://www.pgatour.com/players/players/player.28697.gaganjeet-bhullar.html"},
{"Name": ["Bilodeau, Kyle"], "Link": "https://www.pgatour.com/players/players/player.39990.kyle-bilodeau.html"},
{"Name": ["Bjerregaard, Lucas"], "Link": "https://www.pgatour.com/players/players/player.33803.lucas-bjerregaard.html"},
{"Name": ["Björk, Alexander"], "Link": "https://www.pgatour.com/players/players/player.34310.alexander-bjoerk.html"},
{"Name": ["Bjørn, Thomas"], "Link": "https://www.pgatour.com/players/players/player.10944.thomas-bjorn.html"},
{"Name": ["Black, Ronnie"], "Link": "https://www.pgatour.com/players/players/player.01093.ronnie-black.html"},
{"Name": ["Blackburn, Woody"], "Link": "https://www.pgatour.com/players/players/player.01095.woody-blackburn.html"},
{"Name": ["Blackmar, Phil"], "Link": "https://www.pgatour.com/players/players/player.01096.phil-blackmar.html"},
{"Name": ["Blair, Zac"], "Link": "https://www.pgatour.com/players/players/player.40058.zac-blair.html"},
{"Name": ["Blake, Jay Don"], "Link": "https://www.pgatour.com/players/players/player.01098.jay-don-blake.html"},
{"Name": ["Blancas, Homero"], "Link": "https://www.pgatour.com/players/players/player.01099.homero-blancas.html"},
{"Name": ["Blanks, Kris"], "Link": "https://www.pgatour.com/players/players/player.28087.kris-blanks.html"},
{"Name": ["Blaum, Ryan"], "Link": "https://www.pgatour.com/players/players/player.27958.ryan-blaum.html"},
{"Name": ["Blixt, Jonas"], "Link": "https://www.pgatour.com/players/players/player.27895.jonas-blixt.html"},
{"Name": ["Bohn, Jason"], "Link": "https://www.pgatour.com/players/players/player.24507.jason-bohn.html"},
{"Name": ["Boros, Guy"], "Link": "https://www.pgatour.com/players/players/player.06214.guy-boros.html"},
{"Name": ["Boros, Julius"], "Link": "https://www.pgatour.com/players/players/player.01108.julius-boros.html"},
{"Name": ["Both, Marcus"], "Link": "https://www.pgatour.com/players/players/player.25335.marcus-both.html"},
{"Name": ["Bourdy, Grégory"], "Link": "https://www.pgatour.com/players/players/player.26525.gregory-bourdy.html"},
{"Name": ["Bowditch, Steven"], "Link": "https://www.pgatour.com/players/players/player.25274.steven-bowditch.html"},
{"Name": ["Bozzelli, Dominic"], "Link": "https://www.pgatour.com/players/players/player.40009.dominic-bozzelli.html"},
{"Name": ["Bradley, Keegan"], "Link": "https://www.pgatour.com/players/players/player.33141.keegan-bradley.html"},
{"Name": ["Bradley, Michael"], "Link": "https://www.pgatour.com/players/players/player.01116.michael-bradley.html"},
{"Name": ["Brooks, Mark"], "Link": "https://www.pgatour.com/players/players/player.01132.mark-brooks.html"},
{"Name": ["Brown, Billy Ray"], "Link": "https://www.pgatour.com/players/players/player.01133.billy-ray-brown.html"},
{"Name": ["Brown, Bud"], "Link": "https://www.pgatour.com/players/players/player.37670.bud-brown.html"},
{"Name": ["Brown, Ken"], "Link": "https://www.pgatour.com/players/players/player.01135.ken-brown.html"},
{"Name": ["Brown, Mark"], "Link": "https://www.pgatour.com/players/players/player.22313.mark-brown.html"},
{"Name": ["Brown, Mark"], "Link": "https://www.pgatour.com/players/players/player.32262.mark-brown.html"},
{"Name": ["Brown, Scott"], "Link": "https://www.pgatour.com/players/players/player.29479.scott-brown.html"},
{"Name": ["Browne, Olin"], "Link": "https://www.pgatour.com/players/players/player.01139.olin-browne.html"},
{"Name": ["Bryan, Wesley"], "Link": "https://www.pgatour.com/players/players/player.48084.wesley-bryan.html"},
{"Name": ["Bryant, Bart"], "Link": "https://www.pgatour.com/players/players/player.01142.bart-bryant.html"},
{"Name": ["Bryant, Brad"], "Link": "https://www.pgatour.com/players/players/player.01143.brad-bryant.html"},
{"Name": ["Burgoon, Bronson"], "Link": "https://www.pgatour.com/players/players/player.29268.bronson-burgoon.html"},
{"Name": ["Burmester, Dean"], "Link": "https://www.pgatour.com/players/players/player.33974.dean-burmester.html"},
{"Name": ["Burns, Bob"], "Link": "https://www.pgatour.com/players/players/player.06809.bob-burns.html"},
{"Name": ["Burns, George"], "Link": "https://www.pgatour.com/players/players/player.01150.george-burns.html"},
{"Name": ["Burns, Sam"], "Link": "https://www.pgatour.com/players/players/player.47504.sam-burns.html"},
{"Name": ["Byman, Bob"], "Link": "https://www.pgatour.com/players/players/player.01155.bob-byman.html"},
{"Name": ["Byrd, Jonathan"], "Link": "https://www.pgatour.com/players/players/player.24925.jonathan-byrd.html"},
{"Name": ["Byrne, James"], "Link": "https://www.pgatour.com/players/players/player.32424.james-byrne.html"},
{"Name": ["Byrum, Curt"], "Link": "https://www.pgatour.com/players/players/player.01156.curt-byrum.html"},
{"Name": ["Byrum, Tom"], "Link": "https://www.pgatour.com/players/players/player.01157.tom-byrum.html"},
{"Name": ["Cabrera, Ángel"], "Link": "https://www.pgatour.com/players/players/player.20848.angel-cabrera.html"},
{"Name": ["Cabrera Bello, Rafa"], "Link": "https://www.pgatour.com/players/players/player.26499.rafa-cabrera-bello.html"},
{"Name": ["Cairns, Brian"], "Link": "https://www.pgatour.com/players/players/player.22789.brian-cairns.html"},
{"Name": ["Calcavecchia, Mark"], "Link": "https://www.pgatour.com/players/players/player.01161.mark-calcavecchia.html"},
{"Name": ["Caldwell, Rex"], "Link": "https://www.pgatour.com/players/players/player.01162.rex-caldwell.html"},
{"Name": ["Campbell, Chad"], "Link": "https://www.pgatour.com/players/players/player.12510.chad-campbell.html"},
{"Name": ["Cantlay, Patrick"], "Link": "https://www.pgatour.com/players/players/player.35450.patrick-cantlay.html"},
{"Name": ["Carnevale, Mark"], "Link": "https://www.pgatour.com/players/players/player.07569.mark-carnevale.html"},
{"Name": ["Carter, Jim"], "Link": "https://www.pgatour.com/players/players/player.01175.jim-carter.html"},
{"Name": ["Casey, Paul"], "Link": "https://www.pgatour.com/players/players/player.25364.paul-casey.html"},
{"Name": ["Casper, Billy"], "Link": "https://www.pgatour.com/players/players/player.01177.billy-casper.html"},
{"Name": ["Castro, Roberto"], "Link": "https://www.pgatour.com/players/players/player.32200.roberto-castro.html"},
{"Name": ["Cauley, Bud"], "Link": "https://www.pgatour.com/players/players/player.34021.bud-cauley.html"},
{"Name": ["Cañizares, Alejandro"], "Link": "https://www.pgatour.com/players/players/player.26500.alejandro-canizares.html"},
{"Name": ["Cejka, Alex"], "Link": "https://www.pgatour.com/players/players/player.20472.alex-cejka.html"},
{"Name": ["Cerrudo, Ron"], "Link": "https://www.pgatour.com/players/players/player.01180.ron-cerrudo.html"},
{"Name": ["Chalmers, Greg"], "Link": "https://www.pgatour.com/players/players/player.20593.greg-chalmers.html"},
{"Name": ["Chamblee, Brandel"], "Link": "https://www.pgatour.com/players/players/player.01185.brandel-chamblee.html"},
{"Name": ["Champ, Cameron"], "Link": "https://www.pgatour.com/players/players/player.52372.cameron-champ.html"},
{"Name": ["Chappell, Kevin"], "Link": "https://www.pgatour.com/players/players/player.32366.kevin-chappell.html"},
{"Name": ["Chawrasia, SSP"], "Link": "https://www.pgatour.com/players/players/player.25203.ssp-chawrasia.html"},
{"Name": ["Chen, T.C."], "Link": "https://www.pgatour.com/players/players/player.01192.t-c--chen.html"},
{"Name": ["Chin, John"], "Link": "https://www.pgatour.com/players/players/player.34306.john-chin.html"},
{"Name": ["Choi, Ho Sung"], "Link": "https://www.pgatour.com/players/players/player.29294.ho-sung-choi.html"},
{"Name": ["Choi, K.J."], "Link": "https://www.pgatour.com/players/players/player.24357.k-j--choi.html"},
{"Name": ["Chopra, Daniel"], "Link": "https://www.pgatour.com/players/players/player.20850.daniel-chopra.html"},
{"Name": ["Cink, Stewart"], "Link": "https://www.pgatour.com/players/players/player.20229.stewart-cink.html"},
{"Name": ["Clampett, Bobby"], "Link": "https://www.pgatour.com/players/players/player.01197.bobby-clampett.html"},
{"Name": ["Clark, Tim"], "Link": "https://www.pgatour.com/players/players/player.23135.tim-clark.html"},
{"Name": ["Clark, Wyndham"], "Link": "https://www.pgatour.com/players/players/player.51766.wyndham-clark.html"},
{"Name": ["Clark II, Michael"], "Link": "https://www.pgatour.com/players/players/player.12388.michael-clark-ii.html"},
{"Name": ["Clarke, Darren"], "Link": "https://www.pgatour.com/players/players/player.19825.darren-clarke.html"},
{"Name": ["Claxton, Will"], "Link": "https://www.pgatour.com/players/players/player.28455.will-claxton.html"},
{"Name": ["Clearwater, Keith"], "Link": "https://www.pgatour.com/players/players/player.01200.keith-clearwater.html"},
{"Name": ["Clements, Lennie"], "Link": "https://www.pgatour.com/players/players/player.01201.lennie-clements.html"},
{"Name": ["Coceres, José"], "Link": "https://www.pgatour.com/players/players/player.19972.jose-coceres.html"},
{"Name": ["Cochran, Russ"], "Link": "https://www.pgatour.com/players/players/player.01203.russ-cochran.html"},
{"Name": ["Coetzee, George"], "Link": "https://www.pgatour.com/players/players/player.28937.george-coetzee.html"},
{"Name": ["Colbert, Jim"], "Link": "https://www.pgatour.com/players/players/player.01205.jim-colbert.html"},
{"Name": ["Cole, Bobby"], "Link": "https://www.pgatour.com/players/players/player.01206.bobby-cole.html"},
{"Name": ["Collins, Chad"], "Link": "https://www.pgatour.com/players/players/player.25720.chad-collins.html"},
{"Name": ["Colsaerts, Nicolas"], "Link": "https://www.pgatour.com/players/players/player.23452.nicolas-colsaerts.html"},
{"Name": ["Conner, Frank"], "Link": "https://www.pgatour.com/players/players/player.01214.frank-conner.html"},
{"Name": ["Conners, Corey"], "Link": "https://www.pgatour.com/players/players/player.39997.corey-conners.html"},
{"Name": ["Coody, Charles"], "Link": "https://www.pgatour.com/players/players/player.01215.charles-coody.html"},
{"Name": ["Cook, Austin"], "Link": "https://www.pgatour.com/players/players/player.46435.austin-cook.html"},
{"Name": ["Cook, John"], "Link": "https://www.pgatour.com/players/players/player.01219.john-cook.html"},
{"Name": ["Couch, Chris"], "Link": "https://www.pgatour.com/players/players/player.11123.chris-couch.html"},
{"Name": ["Couples, Fred"], "Link": "https://www.pgatour.com/players/players/player.01226.fred-couples.html"},
{"Name": ["Crampton, Bruce"], "Link": "https://www.pgatour.com/players/players/player.01233.bruce-crampton.html"},
{"Name": ["Crane, Ben"], "Link": "https://www.pgatour.com/players/players/player.23541.ben-crane.html"},
{"Name": ["Crenshaw, Ben"], "Link": "https://www.pgatour.com/players/players/player.01235.ben-crenshaw.html"},
{"Name": ["Curl, Rod"], "Link": "https://www.pgatour.com/players/players/player.01242.rod-curl.html"},
{"Name": ["Curran, Jon"], "Link": "https://www.pgatour.com/players/players/player.34262.jon-curran.html"},
{"Name": ["Curtis, Ben"], "Link": "https://www.pgatour.com/players/players/player.22621.ben-curtis.html"},
{"Name": ["Dahmen, Joel"], "Link": "https://www.pgatour.com/players/players/player.34076.joel-dahmen.html"},
{"Name": ["Daly, John"], "Link": "https://www.pgatour.com/players/players/player.01249.john-daly.html"},
{"Name": ["Damron, Robert"], "Link": "https://www.pgatour.com/players/players/player.19881.robert-damron.html"},
{"Name": ["Davis, Brian"], "Link": "https://www.pgatour.com/players/players/player.21753.brian-davis.html"},
{"Name": ["Davis, Cameron"], "Link": "https://www.pgatour.com/players/players/player.45157.cameron-davis.html"},
{"Name": ["Dawson, Marco"], "Link": "https://www.pgatour.com/players/players/player.06034.marco-dawson.html"},
{"Name": ["Day, Glen"], "Link": "https://www.pgatour.com/players/players/player.08931.glen-day.html"},
{"Name": ["Day, Jason"], "Link": "https://www.pgatour.com/players/players/player.28089.jason-day.html"},
{"Name": ["de Jonge, Brendon"], "Link": "https://www.pgatour.com/players/players/player.23638.brendon-de-jonge.html"},
{"Name": ["De Vicenzo, Roberto"], "Link": "https://www.pgatour.com/players/players/player.05163.roberto-de-vicenzo.html"},
{"Name": ["DeChambeau, Bryson"], "Link": "https://www.pgatour.com/players/players/player.47959.bryson-dechambeau.html"},
{"Name": ["DeLaet, Graham"], "Link": "https://www.pgatour.com/players/players/player.27436.graham-delaet.html"},
{"Name": ["Delsing, Jay"], "Link": "https://www.pgatour.com/players/players/player.01261.jay-delsing.html"},
{"Name": ["Dent, Jim"], "Link": "https://www.pgatour.com/players/players/player.01268.jim-dent.html"},
{"Name": ["Devlin, Bruce"], "Link": "https://www.pgatour.com/players/players/player.01269.bruce-devlin.html"},
{"Name": ["Dickson, Bob"], "Link": "https://www.pgatour.com/players/players/player.01274.bob-dickson.html"},
{"Name": ["Diehl, Terry"], "Link": "https://www.pgatour.com/players/players/player.01275.terry-diehl.html"},
{"Name": ["Dill, Terry"], "Link": "https://www.pgatour.com/players/players/player.01277.terry-dill.html"},
{"Name": ["DiMarco, Chris"], "Link": "https://www.pgatour.com/players/players/player.06251.chris-dimarco.html"},
{"Name": ["Dobyns, Matt"], "Link": "https://www.pgatour.com/players/players/player.36983.matt-dobyns.html"},
{"Name": ["Dodds, Trevor"], "Link": "https://www.pgatour.com/players/players/player.01282.trevor-dodds.html"},
{"Name": ["Dodt, Andrew"], "Link": "https://www.pgatour.com/players/players/player.28751.andrew-dodt.html"},
{"Name": ["Donald, Luke"], "Link": "https://www.pgatour.com/players/players/player.23983.luke-donald.html"},
{"Name": ["Donald, Mike"], "Link": "https://www.pgatour.com/players/players/player.01284.mike-donald.html"},
{"Name": ["Donaldson, Jamie"], "Link": "https://www.pgatour.com/players/players/player.25369.jamie-donaldson.html"},
{"Name": ["Dougherty, Ed"], "Link": "https://www.pgatour.com/players/players/player.01288.ed-dougherty.html"},
{"Name": ["Dougherty, Sean"], "Link": "https://www.pgatour.com/players/players/player.32485.sean-dougherty.html"},
{"Name": ["Douglass, Dale"], "Link": "https://www.pgatour.com/players/players/player.01290.dale-douglass.html"},
{"Name": ["Dredge, Bradley"], "Link": "https://www.pgatour.com/players/players/player.22983.bradley-dredge.html"},
{"Name": ["Dubuisson, Victor"], "Link": "https://www.pgatour.com/players/players/player.28339.victor-dubuisson.html"},
{"Name": ["Dufner, Jason"], "Link": "https://www.pgatour.com/players/players/player.25686.jason-dufner.html"},
{"Name": ["Duke, Ken"], "Link": "https://www.pgatour.com/players/players/player.20104.ken-duke.html"},
{"Name": ["Duncan, Tyler"], "Link": "https://www.pgatour.com/players/players/player.45609.tyler-duncan.html"},
{"Name": ["Dunne, Paul"], "Link": "https://www.pgatour.com/players/players/player.46567.paul-dunne.html"},
{"Name": ["Durant, Joe"], "Link": "https://www.pgatour.com/players/players/player.06621.joe-durant.html"},
{"Name": ["Duval, David"], "Link": "https://www.pgatour.com/players/players/player.09011.david-duval.html"},
{"Name": ["Dyson, Simon"], "Link": "https://www.pgatour.com/players/players/player.24512.simon-dyson.html"},
{"Name": ["Díaz, Roberto"], "Link": "https://www.pgatour.com/players/players/player.35376.roberto-diaz.html"},
{"Name": ["Eastwood, Bob"], "Link": "https://www.pgatour.com/players/players/player.01303.bob-eastwood.html"},
{"Name": ["Edwards, Danny"], "Link": "https://www.pgatour.com/players/players/player.01305.danny-edwards.html"},
{"Name": ["Edwards, David"], "Link": "https://www.pgatour.com/players/players/player.01306.david-edwards.html"},
{"Name": ["Edwards, Joel"], "Link": "https://www.pgatour.com/players/players/player.01307.joel-edwards.html"},
{"Name": ["Eichelberger, Dave"], "Link": "https://www.pgatour.com/players/players/player.01310.dave-eichelberger.html"},
{"Name": ["Elder, Lee"], "Link": "https://www.pgatour.com/players/players/player.01312.lee-elder.html"},
{"Name": ["Elkington, Steve"], "Link": "https://www.pgatour.com/players/players/player.01313.steve-elkington.html"},
{"Name": ["Els, Ernie"], "Link": "https://www.pgatour.com/players/players/player.06522.ernie-els.html"},
{"Name": ["English, Harris"], "Link": "https://www.pgatour.com/players/players/player.34099.harris-english.html"},
{"Name": ["Ernst, Derek"], "Link": "https://www.pgatour.com/players/players/player.37273.derek-ernst.html"},
{"Name": ["Estes, Bob"], "Link": "https://www.pgatour.com/players/players/player.01320.bob-estes.html"},
{"Name": ["Etulain, Julián"], "Link": "https://www.pgatour.com/players/players/player.30191.julian-etulain.html"},
{"Name": ["Every, Matt"], "Link": "https://www.pgatour.com/players/players/player.28307.matt-every.html"},
{"Name": ["Fabel, Brad"], "Link": "https://www.pgatour.com/players/players/player.01323.brad-fabel.html"},
{"Name": ["Faldo, Nick"], "Link": "https://www.pgatour.com/players/players/player.01326.nick-faldo.html"},
{"Name": ["Fathauer, Derek"], "Link": "https://www.pgatour.com/players/players/player.31416.derek-fathauer.html"},
{"Name": ["Faxon, Brad"], "Link": "https://www.pgatour.com/players/players/player.01329.brad-faxon.html"},
{"Name": ["Fehr, Rick"], "Link": "https://www.pgatour.com/players/players/player.01331.rick-fehr.html"},
{"Name": ["Fergus, Keith"], "Link": "https://www.pgatour.com/players/players/player.01334.keith-fergus.html"},
{"Name": ["Ferree, Jim"], "Link": "https://www.pgatour.com/players/players/player.01337.jim-ferree.html"},
{"Name": ["Fezler, Forrest"], "Link": "https://www.pgatour.com/players/players/player.01342.forrest-fezler.html"},
{"Name": ["Finau, Tony"], "Link": "https://www.pgatour.com/players/players/player.29725.tony-finau.html"},
{"Name": ["Finsterwald, Dow"], "Link": "https://www.pgatour.com/players/players/player.01345.dow-finsterwald.html"},
{"Name": ["Fiori, Ed"], "Link": "https://www.pgatour.com/players/players/player.01346.ed-fiori.html"},
{"Name": ["Fisher, Ross"], "Link": "https://www.pgatour.com/players/players/player.27896.ross-fisher.html"},
{"Name": ["Fitzpatrick, Matthew"], "Link": "https://www.pgatour.com/players/players/player.40098.matthew-fitzpatrick.html"},
{"Name": ["Fitzsimons, Pat"], "Link": "https://www.pgatour.com/players/players/player.01350.pat-fitzsimons.html"},
{"Name": ["Fleckman, Marty"], "Link": "https://www.pgatour.com/players/players/player.01352.marty-fleckman.html"},
{"Name": ["Fleetwood, Tommy"], "Link": "https://www.pgatour.com/players/players/player.30911.tommy-fleetwood.html"},
{"Name": ["Fleisher, Bruce"], "Link": "https://www.pgatour.com/players/players/player.01353.bruce-fleisher.html"},
{"Name": ["Flesch, Steve"], "Link": "https://www.pgatour.com/players/players/player.07457.steve-flesch.html"},
{"Name": ["Floyd, Raymond"], "Link": "https://www.pgatour.com/players/players/player.01355.raymond-floyd.html"},
{"Name": ["Ford, Doug"], "Link": "https://www.pgatour.com/players/players/player.01359.doug-ford.html"},
{"Name": ["Forsman, Dan"], "Link": "https://www.pgatour.com/players/players/player.01361.dan-forsman.html"},
{"Name": ["Fought, John"], "Link": "https://www.pgatour.com/players/players/player.01363.john-fought.html"},
{"Name": ["Fowler, Rickie"], "Link": "https://www.pgatour.com/players/players/player.32102.rickie-fowler.html"},
{"Name": ["Fox, Ryan"], "Link": "https://www.pgatour.com/players/players/player.29936.ryan-fox.html"},
{"Name": ["Franco, Carlos"], "Link": "https://www.pgatour.com/players/players/player.12823.carlos-franco.html"},
{"Name": ["Frazar, Harrison"], "Link": "https://www.pgatour.com/players/players/player.21805.harrison-frazar.html"},
{"Name": ["Freeman, Robin"], "Link": "https://www.pgatour.com/players/players/player.01374.robin-freeman.html"},
{"Name": ["Frittelli, Dylan"], "Link": "https://www.pgatour.com/players/players/player.29970.dylan-frittelli.html"},
{"Name": ["Frost, Charles"], "Link": "https://www.pgatour.com/players/players/player.33181.charles-frost.html"},
{"Name": ["Frost, David"], "Link": "https://www.pgatour.com/players/players/player.01378.david-frost.html"},
{"Name": ["Fujimoto, Yoshinori"], "Link": "https://www.pgatour.com/players/players/player.29833.yoshinori-fujimoto.html"},
{"Name": ["Fujita, Hiroyuki"], "Link": "https://www.pgatour.com/players/players/player.21284.hiroyuki-fujita.html"},
{"Name": ["Funk, Fred"], "Link": "https://www.pgatour.com/players/players/player.01381.fred-funk.html"},
{"Name": ["Furyk, Jim"], "Link": "https://www.pgatour.com/players/players/player.10809.jim-furyk.html"},
{"Name": ["Gaffney, Brian"], "Link": "https://www.pgatour.com/players/players/player.23366.brian-gaffney.html"},
{"Name": ["Gainey, Tommy"], "Link": "https://www.pgatour.com/players/players/player.30750.tommy-gainey.html"},
{"Name": ["Gallacher, Stephen"], "Link": "https://www.pgatour.com/players/players/player.20376.stephen-gallacher.html"},
{"Name": ["Gallagher, Jr., Jim"], "Link": "https://www.pgatour.com/players/players/player.01385.jim-gallagher--jr-.html"},
{"Name": ["Gamez, Robert"], "Link": "https://www.pgatour.com/players/players/player.01388.robert-gamez.html"},
{"Name": ["Garber, Joey"], "Link": "https://www.pgatour.com/players/players/player.46523.joey-garber.html"},
{"Name": ["Garcia, Sergio"], "Link": "https://www.pgatour.com/players/players/player.21209.sergio-garcia.html"},
{"Name": ["Gardner, Buddy"], "Link": "https://www.pgatour.com/players/players/player.01390.buddy-gardner.html"},
{"Name": ["Garnett, Brice"], "Link": "https://www.pgatour.com/players/players/player.29535.brice-garnett.html"},
{"Name": ["Garrigus, Robert"], "Link": "https://www.pgatour.com/players/players/player.24358.robert-garrigus.html"},
{"Name": ["Gay, Brian"], "Link": "https://www.pgatour.com/players/players/player.19846.brian-gay.html"},
{"Name": ["Geiberger, Al"], "Link": "https://www.pgatour.com/players/players/player.01401.al-geiberger.html"},
{"Name": ["Geiberger, Brent"], "Link": "https://www.pgatour.com/players/players/player.12645.brent-geiberger.html"},
{"Name": ["Gibson, Kelly"], "Link": "https://www.pgatour.com/players/players/player.01408.kelly-gibson.html"},
{"Name": ["Gilbert, Gibby"], "Link": "https://www.pgatour.com/players/players/player.01412.gibby-gilbert.html"},
{"Name": ["Gilder, Bob"], "Link": "https://www.pgatour.com/players/players/player.01414.bob-gilder.html"},
{"Name": ["Gillespie, Nick"], "Link": "https://www.pgatour.com/players/players/player.31626.nick-gillespie.html"},
{"Name": ["Glasson, Bill"], "Link": "https://www.pgatour.com/players/players/player.01418.bill-glasson.html"},
{"Name": ["Glover, Lucas"], "Link": "https://www.pgatour.com/players/players/player.25900.lucas-glover.html"},
{"Name": ["Glover, Randy"], "Link": "https://www.pgatour.com/players/players/player.01421.randy-glover.html"},
{"Name": ["Goalby, Bob"], "Link": "https://www.pgatour.com/players/players/player.01422.bob-goalby.html"},
{"Name": ["Gogel, Matt"], "Link": "https://www.pgatour.com/players/players/player.10201.matt-gogel.html"},
{"Name": ["Gonzalez, Ernie"], "Link": "https://www.pgatour.com/players/players/player.01425.ernie-gonzalez.html"},
{"Name": ["Gooch, Talor"], "Link": "https://www.pgatour.com/players/players/player.46402.talor-gooch.html"},
{"Name": ["Goosen, Retief"], "Link": "https://www.pgatour.com/players/players/player.20157.retief-goosen.html"},
{"Name": ["Gore, Jason"], "Link": "https://www.pgatour.com/players/players/player.22892.jason-gore.html"},
{"Name": ["Gossett, David"], "Link": "https://www.pgatour.com/players/players/player.23338.david-gossett.html"},
{"Name": ["Goydos, Paul"], "Link": "https://www.pgatour.com/players/players/player.06643.paul-goydos.html"},
{"Name": ["Grace, Branden"], "Link": "https://www.pgatour.com/players/players/player.29974.branden-grace.html"},
{"Name": ["Graham, David"], "Link": "https://www.pgatour.com/players/players/player.01436.david-graham.html"},
{"Name": ["Green, Hubert"], "Link": "https://www.pgatour.com/players/players/player.01443.hubert-green.html"},
{"Name": ["Green, Ken"], "Link": "https://www.pgatour.com/players/players/player.01444.ken-green.html"},
{"Name": ["Green, Nathan"], "Link": "https://www.pgatour.com/players/players/player.23718.nathan-green.html"},
{"Name": ["Gribble, Cody"], "Link": "https://www.pgatour.com/players/players/player.39954.cody-gribble.html"},
{"Name": ["Grillo, Emiliano"], "Link": "https://www.pgatour.com/players/players/player.31646.emiliano-grillo.html"},
{"Name": ["Grob, Mike"], "Link": "https://www.pgatour.com/players/players/player.07941.mike-grob.html"},
{"Name": ["Groh, Gary"], "Link": "https://www.pgatour.com/players/players/player.01450.gary-groh.html"},
{"Name": ["Gump, Scott"], "Link": "https://www.pgatour.com/players/players/player.06044.scott-gump.html"},
{"Name": ["Gómez, Fabián"], "Link": "https://www.pgatour.com/players/players/player.28679.fabian-gomez.html"},
{"Name": ["Haas, Bill"], "Link": "https://www.pgatour.com/players/players/player.24924.bill-haas.html"},
{"Name": ["Haas, Jay"], "Link": "https://www.pgatour.com/players/players/player.01457.jay-haas.html"},
{"Name": ["Hadley, Chesson"], "Link": "https://www.pgatour.com/players/players/player.34563.chesson-hadley.html"},
{"Name": ["Hadwin, Adam"], "Link": "https://www.pgatour.com/players/players/player.33399.adam-hadwin.html"},
{"Name": ["Hagen, Walter"], "Link": "https://www.pgatour.com/players/players/player.15388.walter-hagen.html"},
{"Name": ["Hagy, Brandon"], "Link": "https://www.pgatour.com/players/players/player.46550.brandon-hagy.html"},
{"Name": ["Hahn, James"], "Link": "https://www.pgatour.com/players/players/player.32448.james-hahn.html"},
{"Name": ["Hahn, John"], "Link": "https://www.pgatour.com/players/players/player.39978.john-hahn.html"},
{"Name": ["Hallberg, Gary"], "Link": "https://www.pgatour.com/players/players/player.01468.gary-hallberg.html"},
{"Name": ["Haller, Ryan"], "Link": "https://www.pgatour.com/players/players/player.25277.ryan-haller.html"},
{"Name": ["Hamilton, Todd"], "Link": "https://www.pgatour.com/players/players/player.01473.todd-hamilton.html"},
{"Name": ["Hammer, Laurie"], "Link": "https://www.pgatour.com/players/players/player.01474.laurie-hammer.html"},
{"Name": ["Hammond, Donnie"], "Link": "https://www.pgatour.com/players/players/player.01475.donnie-hammond.html"},
{"Name": ["Han, Seungsu"], "Link": "https://www.pgatour.com/players/players/player.27324.seungsu-han.html"},
{"Name": ["Hancock, Phillip"], "Link": "https://www.pgatour.com/players/players/player.01477.phillip-hancock.html"},
{"Name": ["Hansen, Anders"], "Link": "https://www.pgatour.com/players/players/player.20859.anders-hansen.html"},
{"Name": ["Hanson, Peter"], "Link": "https://www.pgatour.com/players/players/player.22792.peter-hanson.html"},
{"Name": ["Harding, Justin"], "Link": "https://www.pgatour.com/players/players/player.28938.justin-harding.html"},
{"Name": ["Harkins, Brandon"], "Link": "https://www.pgatour.com/players/players/player.35421.brandon-harkins.html"},
{"Name": ["Harman, Brian"], "Link": "https://www.pgatour.com/players/players/player.27644.brian-harman.html"},
{"Name": ["Harrington, Padraig"], "Link": "https://www.pgatour.com/players/players/player.20766.padraig-harrington.html"},
{"Name": ["Harris, Labron"], "Link": "https://www.pgatour.com/players/players/player.01486.labron-harris.html"},
{"Name": ["Hart, Dudley"], "Link": "https://www.pgatour.com/players/players/player.06575.dudley-hart.html"},
{"Name": ["Hatalsky, Morris"], "Link": "https://www.pgatour.com/players/players/player.01495.morris-hatalsky.html"},
{"Name": ["Hatton, Tyrrell"], "Link": "https://www.pgatour.com/players/players/player.34363.tyrrell-hatton.html"},
{"Name": ["Hayes, J.P."], "Link": "https://www.pgatour.com/players/players/player.08537.j-p--hayes.html"},
{"Name": ["Heard, Jerry"], "Link": "https://www.pgatour.com/players/players/player.01502.jerry-heard.html"},
{"Name": ["Hearn, David"], "Link": "https://www.pgatour.com/players/players/player.26758.david-hearn.html"},
{"Name": ["Hebert, Benjamin"], "Link": "https://www.pgatour.com/players/players/player.30812.benjamin-hebert.html"},
{"Name": ["Heinen, Mike"], "Link": "https://www.pgatour.com/players/players/player.08337.mike-heinen.html"},
{"Name": ["Helminen, Ryan"], "Link": "https://www.pgatour.com/players/players/player.28380.ryan-helminen.html"},
{"Name": ["Henke, Nolan"], "Link": "https://www.pgatour.com/players/players/player.01510.nolan-henke.html"},
{"Name": ["Henley, Russell"], "Link": "https://www.pgatour.com/players/players/player.34098.russell-henley.html"},
{"Name": ["Henninger, Brian"], "Link": "https://www.pgatour.com/players/players/player.06617.brian-henninger.html"},
{"Name": ["Henry, Bunky"], "Link": "https://www.pgatour.com/players/players/player.01512.bunky-henry.html"},
{"Name": ["Henry, J.J."], "Link": "https://www.pgatour.com/players/players/player.23353.j-j--henry.html"},
{"Name": ["Hensby, Mark"], "Link": "https://www.pgatour.com/players/players/player.20433.mark-hensby.html"},
{"Name": ["Herman, Jim"], "Link": "https://www.pgatour.com/players/players/player.31557.jim-herman.html"},
{"Name": ["Herron, Tim"], "Link": "https://www.pgatour.com/players/players/player.12782.tim-herron.html"},
{"Name": ["Hickok, Kramer"], "Link": "https://www.pgatour.com/players/players/player.49298.kramer-hickok.html"},
{"Name": ["Hinkle, Lon"], "Link": "https://www.pgatour.com/players/players/player.01522.lon-hinkle.html"},
{"Name": ["Hinson, Larry"], "Link": "https://www.pgatour.com/players/players/player.01524.larry-hinson.html"},
{"Name": ["Hiskey, Babe"], "Link": "https://www.pgatour.com/players/players/player.01525.babe-hiskey.html"},
{"Name": ["Hjertstedt, Gabriel"], "Link": "https://www.pgatour.com/players/players/player.21007.gabriel-hjertstedt.html"},
{"Name": ["Hoch, Scott"], "Link": "https://www.pgatour.com/players/players/player.01527.scott-hoch.html"},
{"Name": ["Hoffman, Charley"], "Link": "https://www.pgatour.com/players/players/player.12716.charley-hoffman.html"},
{"Name": ["Hoffmann, Morgan"], "Link": "https://www.pgatour.com/players/players/player.33461.morgan-hoffmann.html"},
{"Name": ["Hogan, Ben"], "Link": "https://www.pgatour.com/players/players/player.01528.ben-hogan.html"},
{"Name": ["Hoge, Tom"], "Link": "https://www.pgatour.com/players/players/player.35532.tom-hoge.html"},
{"Name": ["Holmes, J.B."], "Link": "https://www.pgatour.com/players/players/player.27141.j-b--holmes.html"},
{"Name": ["Homa, Max"], "Link": "https://www.pgatour.com/players/players/player.39977.max-homa.html"},
{"Name": ["Horschel, Billy"], "Link": "https://www.pgatour.com/players/players/player.29420.billy-horschel.html"},
{"Name": ["Hossler, Beau"], "Link": "https://www.pgatour.com/players/players/player.35461.beau-hossler.html"},
{"Name": ["Hovland, Viktor"], "Link": "https://www.pgatour.com/players/players/player.46717.viktor-hovland.html"},
{"Name": ["Howell, David"], "Link": "https://www.pgatour.com/players/players/player.20608.david-howell.html"},
{"Name": ["Howell III, Charles"], "Link": "https://www.pgatour.com/players/players/player.21961.charles-howell-iii.html"},
{"Name": ["Hughes, Mackenzie"], "Link": "https://www.pgatour.com/players/players/player.35506.mackenzie-hughes.html"},
{"Name": ["Huh, John"], "Link": "https://www.pgatour.com/players/players/player.34174.john-huh.html"},
{"Name": ["Hulbert, Mike"], "Link": "https://www.pgatour.com/players/players/player.01549.mike-hulbert.html"},
{"Name": ["Hurley III, Billy"], "Link": "https://www.pgatour.com/players/players/player.29222.billy-hurley-iii.html"},
{"Name": ["Huston, John"], "Link": "https://www.pgatour.com/players/players/player.01553.john-huston.html"},
{"Name": ["Ikeda, Yuta"], "Link": "https://www.pgatour.com/players/players/player.26908.yuta-ikeda.html"},
{"Name": ["Ilonen, Mikko"], "Link": "https://www.pgatour.com/players/players/player.24956.mikko-ilonen.html"},
{"Name": ["Im, Sungjae"], "Link": "https://www.pgatour.com/players/players/player.39971.sungjae-im.html"},
{"Name": ["Imada, Ryuji"], "Link": "https://www.pgatour.com/players/players/player.21350.ryuji-imada.html"},
{"Name": ["Immelman, Trevor"], "Link": "https://www.pgatour.com/players/players/player.22378.trevor-immelman.html"},
{"Name": ["Inman, Joe"], "Link": "https://www.pgatour.com/players/players/player.01556.joe-inman.html"},
{"Name": ["Inman, John"], "Link": "https://www.pgatour.com/players/players/player.01557.john-inman.html"},
{"Name": ["Irwin, Hale"], "Link": "https://www.pgatour.com/players/players/player.01559.hale-irwin.html"},
{"Name": ["Iverson, Don"], "Link": "https://www.pgatour.com/players/players/player.01562.don-iverson.html"},
{"Name": ["Jacklin, Tony"], "Link": "https://www.pgatour.com/players/players/player.06306.tony-jacklin.html"},
{"Name": ["Jacobs, Tommy"], "Link": "https://www.pgatour.com/players/players/player.01570.tommy-jacobs.html"},
{"Name": ["Jacobsen, Peter"], "Link": "https://www.pgatour.com/players/players/player.01569.peter-jacobsen.html"},
{"Name": ["Jacobson, Freddie"], "Link": "https://www.pgatour.com/players/players/player.21731.freddie-jacobson.html"},
{"Name": ["Jaeckel, Barry"], "Link": "https://www.pgatour.com/players/players/player.01571.barry-jaeckel.html"},
{"Name": ["Jaeger, Stephan"], "Link": "https://www.pgatour.com/players/players/player.36799.stephan-jaeger.html"},
{"Name": ["Jaidee, Thongchai"], "Link": "https://www.pgatour.com/players/players/player.24511.thongchai-jaidee.html"},
{"Name": ["Jamieson, Jim"], "Link": "https://www.pgatour.com/players/players/player.01573.jim-jamieson.html"},
{"Name": ["Jamieson, Scott"], "Link": "https://www.pgatour.com/players/players/player.31138.scott-jamieson.html"},
{"Name": ["January, Don"], "Link": "https://www.pgatour.com/players/players/player.01576.don-january.html"},
{"Name": ["Janzen, Lee"], "Link": "https://www.pgatour.com/players/players/player.01577.lee-janzen.html"},
{"Name": ["Jenkins, Tom"], "Link": "https://www.pgatour.com/players/players/player.01578.tom-jenkins.html"},
{"Name": ["Jeong, Jin"], "Link": "https://www.pgatour.com/players/players/player.32878.jin-jeong.html"},
{"Name": ["Jin, Cheng"], "Link": "https://www.pgatour.com/players/players/player.39826.cheng-jin.html"},
{"Name": ["Jobe, Brandt"], "Link": "https://www.pgatour.com/players/players/player.06573.brandt-jobe.html"},
{"Name": ["Johnson, Dustin"], "Link": "https://www.pgatour.com/players/players/player.30925.dustin-johnson.html"},
{"Name": ["Johnson, Richard"], "Link": "https://www.pgatour.com/players/players/player.26420.richard-johnson.html"},
{"Name": ["Johnson, Zach"], "Link": "https://www.pgatour.com/players/players/player.24024.zach-johnson.html"},
{"Name": ["Johnston, Al"], "Link": "https://www.pgatour.com/players/players/player.01590.al-johnston.html"},
{"Name": ["Johnston, Bill"], "Link": "https://www.pgatour.com/players/players/player.01591.bill-johnston.html"},
{"Name": ["Jones, Brendan"], "Link": "https://www.pgatour.com/players/players/player.23725.brendan-jones.html"},
{"Name": ["Jones, Brett"], "Link": "https://www.pgatour.com/players/players/player.28327.brett-jones.html"},
{"Name": ["Jones, Grier"], "Link": "https://www.pgatour.com/players/players/player.01597.grier-jones.html"},
{"Name": ["Jones, Kent"], "Link": "https://www.pgatour.com/players/players/player.10733.kent-jones.html"},
{"Name": ["Jones, Kyle"], "Link": "https://www.pgatour.com/players/players/player.47990.kyle-jones.html"},
{"Name": ["Jones, Matt"], "Link": "https://www.pgatour.com/players/players/player.26300.matt-jones.html"},
{"Name": ["Jones, Steve"], "Link": "https://www.pgatour.com/players/players/player.01599.steve-jones.html"},
{"Name": ["Kang, Jiman"], "Link": "https://www.pgatour.com/players/players/player.25400.jiman-kang.html"},
{"Name": ["Kang, Sung"], "Link": "https://www.pgatour.com/players/players/player.27974.sung-kang.html"},
{"Name": ["Karl, Richie"], "Link": "https://www.pgatour.com/players/players/player.01611.richie-karl.html"},
{"Name": ["Karlberg, Rikard"], "Link": "https://www.pgatour.com/players/players/player.27899.rikard-karlberg.html"},
{"Name": ["Karlsson, Robert"], "Link": "https://www.pgatour.com/players/players/player.19970.robert-karlsson.html"},
{"Name": ["Kaufman, Smylie"], "Link": "https://www.pgatour.com/players/players/player.46440.smylie-kaufman.html"},
{"Name": ["Kaye, Jonathan"], "Link": "https://www.pgatour.com/players/players/player.20094.jonathan-kaye.html"},
{"Name": ["Kaymer, Martin"], "Link": "https://www.pgatour.com/players/players/player.27408.martin-kaymer.html"},
{"Name": ["Kelly, Andrew"], "Link": "https://www.pgatour.com/players/players/player.34471.andrew-kelly.html"},
{"Name": ["Kelly, Jerry"], "Link": "https://www.pgatour.com/players/players/player.08075.jerry-kelly.html"},
{"Name": ["Kelly, Troy"], "Link": "https://www.pgatour.com/players/players/player.28308.troy-kelly.html"},
{"Name": ["Kendall, Skip"], "Link": "https://www.pgatour.com/players/players/player.01619.skip-kendall.html"},
{"Name": ["Kennedy, Ryan"], "Link": "https://www.pgatour.com/players/players/player.47225.ryan-kennedy.html"},
{"Name": ["Kim, Anthony"], "Link": "https://www.pgatour.com/players/players/player.29718.anthony-kim.html"},
{"Name": ["Kim, Chan"], "Link": "https://www.pgatour.com/players/players/player.34587.chan-kim.html"},
{"Name": ["Kim, Hyung-Sung"], "Link": "https://www.pgatour.com/players/players/player.37092.hyung-sung-kim.html"},
{"Name": ["Kim, K.T."], "Link": "https://www.pgatour.com/players/players/player.28258.k-t--kim.html"},
{"Name": ["Kim, Michael"], "Link": "https://www.pgatour.com/players/players/player.39975.michael-kim.html"},
{"Name": ["Kim, Si Woo"], "Link": "https://www.pgatour.com/players/players/player.37455.si-woo-kim.html"},
{"Name": ["Kim, Whee"], "Link": "https://www.pgatour.com/players/players/player.37454.whee-kim.html"},
{"Name": ["Kirk, Chris"], "Link": "https://www.pgatour.com/players/players/player.30926.chris-kirk.html"},
{"Name": ["Kisner, Kevin"], "Link": "https://www.pgatour.com/players/players/player.29478.kevin-kisner.html"},
{"Name": ["Kite, Tom"], "Link": "https://www.pgatour.com/players/players/player.01633.tom-kite.html"},
{"Name": ["Kizzire, Patton"], "Link": "https://www.pgatour.com/players/players/player.32757.patton-kizzire.html"},
{"Name": ["Kjeldsen, Søren"], "Link": "https://www.pgatour.com/players/players/player.22986.soren-kjeldsen.html"},
{"Name": ["Knost, Colt"], "Link": "https://www.pgatour.com/players/players/player.30711.colt-knost.html"},
{"Name": ["Knous, Jim"], "Link": "https://www.pgatour.com/players/players/player.36852.jim-knous.html"},
{"Name": ["Knox, Kenny"], "Link": "https://www.pgatour.com/players/players/player.01639.kenny-knox.html"},
{"Name": ["Knox, Russell"], "Link": "https://www.pgatour.com/players/players/player.33122.russell-knox.html"},
{"Name": ["Koch, Gary"], "Link": "https://www.pgatour.com/players/players/player.01641.gary-koch.html"},
{"Name": ["Kodaira, Satoshi"], "Link": "https://www.pgatour.com/players/players/player.32816.satoshi-kodaira.html"},
{"Name": ["Koepka, Brooks"], "Link": "https://www.pgatour.com/players/players/player.36689.brooks-koepka.html"},
{"Name": ["Kok, Johan"], "Link": "https://www.pgatour.com/players/players/player.27652.johan-kok.html"},
{"Name": ["Kokrak, Jason"], "Link": "https://www.pgatour.com/players/players/player.30944.jason-kokrak.html"},
{"Name": ["Kondo, Tomohiro"], "Link": "https://www.pgatour.com/players/players/player.22032.tomohiro-kondo.html"},
{"Name": ["Kraft, Greg"], "Link": "https://www.pgatour.com/players/players/player.06012.greg-kraft.html"},
{"Name": ["Kraft, Kelly"], "Link": "https://www.pgatour.com/players/players/player.35879.kelly-kraft.html"},
{"Name": ["Kratzert, Billy"], "Link": "https://www.pgatour.com/players/players/player.01648.billy-kratzert.html"},
{"Name": ["Kuchar, Matt"], "Link": "https://www.pgatour.com/players/players/player.23108.matt-kuchar.html"},
{"Name": ["Kuehne, Hank"], "Link": "https://www.pgatour.com/players/players/player.23552.hank-kuehne.html"},
{"Name": ["Lahiri, Anirban"], "Link": "https://www.pgatour.com/players/players/player.31420.anirban-lahiri.html"},
{"Name": ["Laird, Martin"], "Link": "https://www.pgatour.com/players/players/player.27936.martin-laird.html"},
{"Name": ["Lamely, Derek"], "Link": "https://www.pgatour.com/players/players/player.27797.derek-lamely.html"},
{"Name": ["Lancaster, Neal"], "Link": "https://www.pgatour.com/players/players/player.06332.neal-lancaster.html"},
{"Name": ["Landry, Andrew"], "Link": "https://www.pgatour.com/players/players/player.33410.andrew-landry.html"},
{"Name": ["Langasque, Romain"], "Link": "https://www.pgatour.com/players/players/player.37250.romain-langasque.html"},
{"Name": ["Langer, Bernhard"], "Link": "https://www.pgatour.com/players/players/player.01666.bernhard-langer.html"},
{"Name": ["Langley, Scott"], "Link": "https://www.pgatour.com/players/players/player.34261.scott-langley.html"},
{"Name": ["Larrazabal, Pablo"], "Link": "https://www.pgatour.com/players/players/player.29670.pablo-larrazabal.html"},
{"Name": ["Lashley, Nate"], "Link": "https://www.pgatour.com/players/players/player.28775.nate-lashley.html"},
{"Name": ["Lawrie, Paul"], "Link": "https://www.pgatour.com/players/players/player.19904.paul-lawrie.html"},
{"Name": ["Lebioda, Hank"], "Link": "https://www.pgatour.com/players/players/player.49766.hank-lebioda.html"},
{"Name": ["Lee, Danny"], "Link": "https://www.pgatour.com/players/players/player.29926.danny-lee.html"},
{"Name": ["Lee, Kyoung-Hoon"], "Link": "https://www.pgatour.com/players/players/player.32791.kyoung-hoon-lee.html"},
{"Name": ["Lee, Lucas"], "Link": "https://www.pgatour.com/players/players/player.32888.lucas-lee.html"},
{"Name": ["Lee, Soomin"], "Link": "https://www.pgatour.com/players/players/player.34168.soomin-lee.html"},
{"Name": ["Lee, Sung-Ho"], "Link": "https://www.pgatour.com/players/players/player.33233.sung-ho-lee.html"},
{"Name": ["Leggatt, Ian"], "Link": "https://www.pgatour.com/players/players/player.10565.ian-leggatt.html"},
{"Name": ["Lehman, Tom"], "Link": "https://www.pgatour.com/players/players/player.01677.tom-lehman.html"},
{"Name": ["Leishman, Marc"], "Link": "https://www.pgatour.com/players/players/player.26851.marc-leishman.html"},
{"Name": ["Leonard, Justin"], "Link": "https://www.pgatour.com/players/players/player.10860.justin-leonard.html"},
{"Name": ["Levi, Wayne"], "Link": "https://www.pgatour.com/players/players/player.01682.wayne-levi.html"},
{"Name": ["Levy, Alexander"], "Link": "https://www.pgatour.com/players/players/player.34579.alexander-levy.html"},
{"Name": ["Lewis, J.L."], "Link": "https://www.pgatour.com/players/players/player.01685.j-l--lewis.html"},
{"Name": ["Li, Haotong"], "Link": "https://www.pgatour.com/players/players/player.35296.haotong-li.html"},
{"Name": ["Lickliter II, Frank"], "Link": "https://www.pgatour.com/players/players/player.11032.frank-lickliter-ii.html"},
{"Name": ["Lindheim, Nicholas"], "Link": "https://www.pgatour.com/players/players/player.37278.nicholas-lindheim.html"},
{"Name": ["Lindsey, Pat"], "Link": "https://www.pgatour.com/players/players/player.01692.pat-lindsey.html"},
{"Name": ["Lingmerth, David"], "Link": "https://www.pgatour.com/players/players/player.34409.david-lingmerth.html"},
{"Name": ["List, Luke"], "Link": "https://www.pgatour.com/players/players/player.27129.luke-list.html"},
{"Name": ["Littler, Gene"], "Link": "https://www.pgatour.com/players/players/player.01695.gene-littler.html"},
{"Name": ["Lohr, Bob"], "Link": "https://www.pgatour.com/players/players/player.01701.bob-lohr.html"},
{"Name": ["Lonard, Peter"], "Link": "https://www.pgatour.com/players/players/player.20634.peter-lonard.html"},
{"Name": ["Long, Adam"], "Link": "https://www.pgatour.com/players/players/player.35449.adam-long.html"},
{"Name": ["Long, Jace"], "Link": "https://www.pgatour.com/players/players/player.39994.jace-long.html"},
{"Name": ["Lott, Lyn"], "Link": "https://www.pgatour.com/players/players/player.01703.lyn-lott.html"},
{"Name": ["Love III, Davis"], "Link": "https://www.pgatour.com/players/players/player.01706.davis-love-iii.html"},
{"Name": ["Lovelady, Tom"], "Link": "https://www.pgatour.com/players/players/player.50526.tom-lovelady.html"},
{"Name": ["Lovemark, Jamie"], "Link": "https://www.pgatour.com/players/players/player.29461.jamie-lovemark.html"},
{"Name": ["Lowery, Steve"], "Link": "https://www.pgatour.com/players/players/player.01707.steve-lowery.html"},
{"Name": ["Lowry, Shane"], "Link": "https://www.pgatour.com/players/players/player.33204.shane-lowry.html"},
{"Name": ["Lu, Chih Wei"], "Link": "https://www.pgatour.com/players/players/player.29064.chih-wei-lu.html"},
{"Name": ["Luck, Curtis"], "Link": "https://www.pgatour.com/players/players/player.37380.curtis-luck.html"},
{"Name": ["Luiten, Joost"], "Link": "https://www.pgatour.com/players/players/player.28300.joost-luiten.html"},
{"Name": ["Lunde, Bill"], "Link": "https://www.pgatour.com/players/players/player.23548.bill-lunde.html"},
{"Name": ["Lunn, Bob"], "Link": "https://www.pgatour.com/players/players/player.01714.bob-lunn.html"},
{"Name": ["Lye, Mark"], "Link": "https://www.pgatour.com/players/players/player.01715.mark-lye.html"},
{"Name": ["Lyle, Sandy"], "Link": "https://www.pgatour.com/players/players/player.01717.sandy-lyle.html"},
{"Name": ["Lynn, David"], "Link": "https://www.pgatour.com/players/players/player.21099.david-lynn.html"},
{"Name": ["MacKenzie, Will"], "Link": "https://www.pgatour.com/players/players/player.24912.will-mackenzie.html"},
{"Name": ["Madsen, Morten Orum"], "Link": "https://www.pgatour.com/players/players/player.32694.morten-orum-madsen.html"},
{"Name": ["Magee, Andrew"], "Link": "https://www.pgatour.com/players/players/player.01723.andrew-magee.html"},
{"Name": ["Maggert, Jeff"], "Link": "https://www.pgatour.com/players/players/player.01724.jeff-maggert.html"},
{"Name": ["Mahaffey, John"], "Link": "https://www.pgatour.com/players/players/player.01725.john-mahaffey.html"},
{"Name": ["Mahan, Hunter"], "Link": "https://www.pgatour.com/players/players/player.24781.hunter-mahan.html"},
{"Name": ["Malnati, Peter"], "Link": "https://www.pgatour.com/players/players/player.34466.peter-malnati.html"},
{"Name": ["Maltbie, Roger"], "Link": "https://www.pgatour.com/players/players/player.01736.roger-maltbie.html"},
{"Name": ["Manassero, Matteo"], "Link": "https://www.pgatour.com/players/players/player.33199.matteo-manassero.html"},
{"Name": ["Marino, Steve"], "Link": "https://www.pgatour.com/players/players/player.28158.steve-marino.html"},
{"Name": ["Marti, Fred"], "Link": "https://www.pgatour.com/players/players/player.01746.fred-marti.html"},
{"Name": ["Martin, Ben"], "Link": "https://www.pgatour.com/players/players/player.33413.ben-martin.html"},
{"Name": ["Maruyama, Daisuke"], "Link": "https://www.pgatour.com/players/players/player.21470.daisuke-maruyama.html"},
{"Name": ["Maruyama, Shigeki"], "Link": "https://www.pgatour.com/players/players/player.12680.shigeki-maruyama.html"},
{"Name": ["Massengale, Rik"], "Link": "https://www.pgatour.com/players/players/player.01753.rik-massengale.html"},
{"Name": ["Mast, Dick"], "Link": "https://www.pgatour.com/players/players/player.01755.dick-mast.html"},
{"Name": ["Matsuyama, Hideki"], "Link": "https://www.pgatour.com/players/players/player.32839.hideki-matsuyama.html"},
{"Name": ["Matteson, Troy"], "Link": "https://www.pgatour.com/players/players/player.27120.troy-matteson.html"},
{"Name": ["Mattiace, Len"], "Link": "https://www.pgatour.com/players/players/player.01761.len-mattiace.html"},
{"Name": ["Maxwell, Billy"], "Link": "https://www.pgatour.com/players/players/player.01763.billy-maxwell.html"},
{"Name": ["Mayfair, Billy"], "Link": "https://www.pgatour.com/players/players/player.01766.billy-mayfair.html"},
{"Name": ["McCallister, Blaine"], "Link": "https://www.pgatour.com/players/players/player.01771.blaine-mccallister.html"},
{"Name": ["McCallister, Bob"], "Link": "https://www.pgatour.com/players/players/player.01772.bob-mccallister.html"},
{"Name": ["McCarron, Scott"], "Link": "https://www.pgatour.com/players/players/player.10585.scott-mccarron.html"},
{"Name": ["McCarthy, Denny"], "Link": "https://www.pgatour.com/players/players/player.47993.denny-mccarthy.html"},
{"Name": ["McCord, Gary"], "Link": "https://www.pgatour.com/players/players/player.01779.gary-mccord.html"},
{"Name": ["McCullough, Mike"], "Link": "https://www.pgatour.com/players/players/player.01782.mike-mccullough.html"},
{"Name": ["McCumber, Mark"], "Link": "https://www.pgatour.com/players/players/player.01783.mark-mccumber.html"},
{"Name": ["McDowell, Graeme"], "Link": "https://www.pgatour.com/players/players/player.25572.graeme-mcdowell.html"},
{"Name": ["McElyea, Cory"], "Link": "https://www.pgatour.com/players/players/player.39976.cory-mcelyea.html"},
{"Name": ["McGee, Jerry"], "Link": "https://www.pgatour.com/players/players/player.01786.jerry-mcgee.html"},
{"Name": ["McGirt, William"], "Link": "https://www.pgatour.com/players/players/player.31202.william-mcgirt.html"},
{"Name": ["McGovern, Jim"], "Link": "https://www.pgatour.com/players/players/player.06090.jim-mcgovern.html"},
{"Name": ["McGowan, Pat"], "Link": "https://www.pgatour.com/players/players/player.01790.pat-mcgowan.html"},
{"Name": ["McIlroy, Rory"], "Link": "https://www.pgatour.com/players/players/player.28237.rory-mcilroy.html"},
{"Name": ["McLachlin, Parker"], "Link": "https://www.pgatour.com/players/players/player.24449.parker-mclachlin.html"},
{"Name": ["McLendon, Mac"], "Link": "https://www.pgatour.com/players/players/player.01793.mac-mclendon.html"},
{"Name": ["McNeill, George"], "Link": "https://www.pgatour.com/players/players/player.24490.george-mcneill.html"},
{"Name": ["McRoy, Spike"], "Link": "https://www.pgatour.com/players/players/player.08339.spike-mcroy.html"},
{"Name": ["Mediate, Rocco"], "Link": "https://www.pgatour.com/players/players/player.01797.rocco-mediate.html"},
{"Name": ["Meesawat, Prom"], "Link": "https://www.pgatour.com/players/players/player.24039.prom-meesawat.html"},
{"Name": ["Merrick, John"], "Link": "https://www.pgatour.com/players/players/player.27933.john-merrick.html"},
{"Name": ["Merritt, Troy"], "Link": "https://www.pgatour.com/players/players/player.32640.troy-merritt.html"},
{"Name": ["Micheel, Shaun"], "Link": "https://www.pgatour.com/players/players/player.06515.shaun-micheel.html"},
{"Name": ["Mickelson, Phil"], "Link": "https://www.pgatour.com/players/players/player.01810.phil-mickelson.html"},
{"Name": ["Middlecoff, Cary"], "Link": "https://www.pgatour.com/players/players/player.01811.cary-middlecoff.html"},
{"Name": ["Miller, Allen"], "Link": "https://www.pgatour.com/players/players/player.01814.allen-miller.html"},
{"Name": ["Miller, Johnny"], "Link": "https://www.pgatour.com/players/players/player.01815.johnny-miller.html"},
{"Name": ["Mitchell, Jeff"], "Link": "https://www.pgatour.com/players/players/player.01821.jeff-mitchell.html"},
{"Name": ["Mitchell, Keith"], "Link": "https://www.pgatour.com/players/players/player.39546.keith-mitchell.html"},
{"Name": ["Mize, Larry"], "Link": "https://www.pgatour.com/players/players/player.01823.larry-mize.html"},
{"Name": ["Molder, Bryce"], "Link": "https://www.pgatour.com/players/players/player.23800.bryce-molder.html"},
{"Name": ["Molinari, Edoardo"], "Link": "https://www.pgatour.com/players/players/player.23814.edoardo-molinari.html"},
{"Name": ["Molinari, Francesco"], "Link": "https://www.pgatour.com/players/players/player.25198.francesco-molinari.html"},
{"Name": ["Moore, Jace"], "Link": "https://www.pgatour.com/players/players/player.39991.jace-moore.html"},
{"Name": ["Moore, Jonathan"], "Link": "https://www.pgatour.com/players/players/player.29422.jonathan-moore.html"},
{"Name": ["Moore, Ryan"], "Link": "https://www.pgatour.com/players/players/player.26596.ryan-moore.html"},
{"Name": ["Morgan, Gil"], "Link": "https://www.pgatour.com/players/players/player.01837.gil-morgan.html"},
{"Name": ["Morgan, John"], "Link": "https://www.pgatour.com/players/players/player.20112.john-morgan.html"},
{"Name": ["Morin, Alan"], "Link": "https://www.pgatour.com/players/players/player.23091.alan-morin.html"},
{"Name": ["Morley, Mike"], "Link": "https://www.pgatour.com/players/players/player.01838.mike-morley.html"},
{"Name": ["Morrison, James"], "Link": "https://www.pgatour.com/players/players/player.29256.james-morrison.html"},
{"Name": ["Morse, John"], "Link": "https://www.pgatour.com/players/players/player.07235.john-morse.html"},
{"Name": ["Mudd, Jodie"], "Link": "https://www.pgatour.com/players/players/player.01846.jodie-mudd.html"},
{"Name": ["Mullinax, Trey"], "Link": "https://www.pgatour.com/players/players/player.46601.trey-mullinax.html"},
{"Name": ["Munson, Brett"], "Link": "https://www.pgatour.com/players/players/player.34451.brett-munson.html"},
{"Name": ["Murphy, Bob"], "Link": "https://www.pgatour.com/players/players/player.01851.bob-murphy.html"},
{"Name": ["Murray, Grayson"], "Link": "https://www.pgatour.com/players/players/player.34213.grayson-murray.html"},
{"Name": ["Muto, Toshinori"], "Link": "https://www.pgatour.com/players/players/player.27118.toshinori-muto.html"},
{"Name": ["Muñoz, Sebastián"], "Link": "https://www.pgatour.com/players/players/player.48822.sebastian-munoz.html"},
{"Name": ["Na, Kevin"], "Link": "https://www.pgatour.com/players/players/player.25396.kevin-na.html"},
{"Name": ["Nelford, Jim"], "Link": "https://www.pgatour.com/players/players/player.01861.jim-nelford.html"},
{"Name": ["Nelson, Byron"], "Link": "https://www.pgatour.com/players/players/player.01863.byron-nelson.html"},
{"Name": ["Nelson, Larry"], "Link": "https://www.pgatour.com/players/players/player.01864.larry-nelson.html"},
{"Name": ["Nevil, Dwight"], "Link": "https://www.pgatour.com/players/players/player.01865.dwight-nevil.html"},
{"Name": ["Newton, Jack"], "Link": "https://www.pgatour.com/players/players/player.01866.jack-newton.html"},
{"Name": ["Nichols, Bobby"], "Link": "https://www.pgatour.com/players/players/player.01867.bobby-nichols.html"},
{"Name": ["Nicklaus, Jack"], "Link": "https://www.pgatour.com/players/players/player.01869.jack-nicklaus.html"},
{"Name": ["Nicolette, Mike"], "Link": "https://www.pgatour.com/players/players/player.01871.mike-nicolette.html"},
{"Name": ["Niemann, Joaquin"], "Link": "https://www.pgatour.com/players/players/player.45486.joaquin-niemann.html"},
{"Name": ["Nieporte, Tom"], "Link": "https://www.pgatour.com/players/players/player.01873.tom-nieporte.html"},
{"Name": ["Nobilo, Frank"], "Link": "https://www.pgatour.com/players/players/player.10457.frank-nobilo.html"},
{"Name": ["Noh, Seung-Yul"], "Link": "https://www.pgatour.com/players/players/player.29289.seung-yul-noh.html"},
{"Name": ["Noren, Alex"], "Link": "https://www.pgatour.com/players/players/player.27349.alex-noren.html"},
{"Name": ["Norman, Greg"], "Link": "https://www.pgatour.com/players/players/player.01876.greg-norman.html"},
{"Name": ["Norris, Shaun"], "Link": "https://www.pgatour.com/players/players/player.26328.shaun-norris.html"},
{"Name": ["Norris, Tim"], "Link": "https://www.pgatour.com/players/players/player.01877.tim-norris.html"},
{"Name": ["North, Andy"], "Link": "https://www.pgatour.com/players/players/player.01878.andy-north.html"},
{"Name": ["O'Grady, Mac"], "Link": "https://www.pgatour.com/players/players/player.01884.mac-o-grady.html"},
{"Name": ["O'Hair, Sean"], "Link": "https://www.pgatour.com/players/players/player.24140.sean-o-hair.html"},
{"Name": ["O'Meara, Mark"], "Link": "https://www.pgatour.com/players/players/player.01887.mark-o-meara.html"},
{"Name": ["Oberholser, Arron"], "Link": "https://www.pgatour.com/players/players/player.20628.arron-oberholser.html"},
{"Name": ["Oda, Koumei"], "Link": "https://www.pgatour.com/players/players/player.27119.koumei-oda.html"},
{"Name": ["Ogilvie, Joe"], "Link": "https://www.pgatour.com/players/players/player.21949.joe-ogilvie.html"},
{"Name": ["Ogilvy, Geoff"], "Link": "https://www.pgatour.com/players/players/player.22046.geoff-ogilvy.html"},
{"Name": ["Ogrin, David"], "Link": "https://www.pgatour.com/players/players/player.01891.david-ogrin.html"},
{"Name": ["Olazábal, José María"], "Link": "https://www.pgatour.com/players/players/player.06373.jose-maria-olazabal.html"},
{"Name": ["Olesen, Thorbjørn"], "Link": "https://www.pgatour.com/players/players/player.33968.thorbjorn-olesen.html"},
{"Name": ["Olson, Jeff"], "Link": "https://www.pgatour.com/players/players/player.34357.jeff-olson.html"},
{"Name": ["Oosterhuis, Peter"], "Link": "https://www.pgatour.com/players/players/player.01897.peter-oosterhuis.html"},
{"Name": ["Oosthuizen, Louis"], "Link": "https://www.pgatour.com/players/players/player.26329.louis-oosthuizen.html"},
{"Name": ["Ormsby, Wade"], "Link": "https://www.pgatour.com/players/players/player.26341.wade-ormsby.html"},
{"Name": ["Ortiz, Carlos"], "Link": "https://www.pgatour.com/players/players/player.33667.carlos-ortiz.html"},
{"Name": ["Otaegui, Adrian"], "Link": "https://www.pgatour.com/players/players/player.34575.adrian-otaegui.html"},
{"Name": ["Otto, Hennie"], "Link": "https://www.pgatour.com/players/players/player.22400.hennie-otto.html"},
{"Name": ["Overton, Jeff"], "Link": "https://www.pgatour.com/players/players/player.28475.jeff-overton.html"},
{"Name": ["Owen, Greg"], "Link": "https://www.pgatour.com/players/players/player.20691.greg-owen.html"},
{"Name": ["Pace, Roy"], "Link": "https://www.pgatour.com/players/players/player.06583.roy-pace.html"},
{"Name": ["Palmer, Arnold"], "Link": "https://www.pgatour.com/players/players/player.01910.arnold-palmer.html"},
{"Name": ["Palmer, Ryan"], "Link": "https://www.pgatour.com/players/players/player.23320.ryan-palmer.html"},
{"Name": ["Pampling, Rod"], "Link": "https://www.pgatour.com/players/players/player.20572.rod-pampling.html"},
{"Name": ["Pan, C.T."], "Link": "https://www.pgatour.com/players/players/player.29908.c-t--pan.html"},
{"Name": ["Park, Sung Joon"], "Link": "https://www.pgatour.com/players/players/player.34130.sung-joon-park.html"},
{"Name": ["Parnevik, Jesper"], "Link": "https://www.pgatour.com/players/players/player.12660.jesper-parnevik.html"},
{"Name": ["Parry, Craig"], "Link": "https://www.pgatour.com/players/players/player.01920.craig-parry.html"},
{"Name": ["Pate, Jerry"], "Link": "https://www.pgatour.com/players/players/player.01925.jerry-pate.html"},
{"Name": ["Pate, Steve"], "Link": "https://www.pgatour.com/players/players/player.01926.steve-pate.html"},
{"Name": ["Paulson, Dennis"], "Link": "https://www.pgatour.com/players/players/player.01927.dennis-paulson.html"},
{"Name": ["Pavin, Corey"], "Link": "https://www.pgatour.com/players/players/player.01928.corey-pavin.html"},
{"Name": ["Pearce, Mahal"], "Link": "https://www.pgatour.com/players/players/player.26561.mahal-pearce.html"},
{"Name": ["Peete, Calvin"], "Link": "https://www.pgatour.com/players/players/player.01935.calvin-peete.html"},
{"Name": ["Peoples, David"], "Link": "https://www.pgatour.com/players/players/player.01938.david-peoples.html"},
{"Name": ["Pepperell, Eddie"], "Link": "https://www.pgatour.com/players/players/player.34709.eddie-pepperell.html"},
{"Name": ["Perez, Pat"], "Link": "https://www.pgatour.com/players/players/player.24361.pat-perez.html"},
{"Name": ["Perks, Craig"], "Link": "https://www.pgatour.com/players/players/player.10912.craig-perks.html"},
{"Name": ["Pernice Jr., Tom"], "Link": "https://www.pgatour.com/players/players/player.01941.tom-pernice-jr-.html"},
{"Name": ["Perry, Chris"], "Link": "https://www.pgatour.com/players/players/player.01943.chris-perry.html"},
{"Name": ["Perry, Kenny"], "Link": "https://www.pgatour.com/players/players/player.01945.kenny-perry.html"},
{"Name": ["Peters, Austin"], "Link": "https://www.pgatour.com/players/players/player.48139.austin-peters.html"},
{"Name": ["Petrovic, Tim"], "Link": "https://www.pgatour.com/players/players/player.01948.tim-petrovic.html"},
{"Name": ["Pettersson, Carl"], "Link": "https://www.pgatour.com/players/players/player.25345.carl-pettersson.html"},
{"Name": ["Pfeil, Mark"], "Link": "https://www.pgatour.com/players/players/player.01949.mark-pfeil.html"},
{"Name": ["Phadungsil, Chinnarat"], "Link": "https://www.pgatour.com/players/players/player.28150.chinnarat-phadungsil.html"},
{"Name": ["Piercy, Scott"], "Link": "https://www.pgatour.com/players/players/player.25818.scott-piercy.html"},
{"Name": ["Pieters, Thomas"], "Link": "https://www.pgatour.com/players/players/player.33293.thomas-pieters.html"},
{"Name": ["Piller, Martin"], "Link": "https://www.pgatour.com/players/players/player.32876.martin-piller.html"},
{"Name": ["Pittayarat, Panuphol"], "Link": "https://www.pgatour.com/players/players/player.33610.panuphol-pittayarat.html"},
{"Name": ["Player, Gary"], "Link": "https://www.pgatour.com/players/players/player.01955.gary-player.html"},
{"Name": ["Pohl, Dan"], "Link": "https://www.pgatour.com/players/players/player.01958.dan-pohl.html"},
{"Name": ["Points, D.A."], "Link": "https://www.pgatour.com/players/players/player.25240.d-a--points.html"},
{"Name": ["Pooley, Don"], "Link": "https://www.pgatour.com/players/players/player.01960.don-pooley.html"},
{"Name": ["Porteous, Haydn"], "Link": "https://www.pgatour.com/players/players/player.35912.haydn-porteous.html"},
{"Name": ["Poston, J.T."], "Link": "https://www.pgatour.com/players/players/player.49771.j-t--poston.html"},
{"Name": ["Pott, Johnny"], "Link": "https://www.pgatour.com/players/players/player.01962.johnny-pott.html"},
{"Name": ["Potter, Jr., Ted"], "Link": "https://www.pgatour.com/players/players/player.27556.ted-potter--jr-.html"},
{"Name": ["Poulter, Ian"], "Link": "https://www.pgatour.com/players/players/player.24138.ian-poulter.html"},
{"Name": ["Power, Seamus"], "Link": "https://www.pgatour.com/players/players/player.28252.seamus-power.html"},
{"Name": ["Powers, Greg"], "Link": "https://www.pgatour.com/players/players/player.01964.greg-powers.html"},
{"Name": ["Price, Nick"], "Link": "https://www.pgatour.com/players/players/player.01968.nick-price.html"},
{"Name": ["Pride, Dicky"], "Link": "https://www.pgatour.com/players/players/player.10213.dicky-pride.html"},
{"Name": ["Prugh, Alex"], "Link": "https://www.pgatour.com/players/players/player.30946.alex-prugh.html"},
{"Name": ["Purdy, Ted"], "Link": "https://www.pgatour.com/players/players/player.21959.ted-purdy.html"},
{"Name": ["Purtzer, Tom"], "Link": "https://www.pgatour.com/players/players/player.01975.tom-purtzer.html"},
{"Name": ["Putnam, Andrew"], "Link": "https://www.pgatour.com/players/players/player.34256.andrew-putnam.html"},
{"Name": ["Quesne, Julien"], "Link": "https://www.pgatour.com/players/players/player.27778.julien-quesne.html"},
{"Name": ["Quigley, Brett"], "Link": "https://www.pgatour.com/players/players/player.07749.brett-quigley.html"},
{"Name": ["Quiros, Alvaro"], "Link": "https://www.pgatour.com/players/players/player.27072.alvaro-quiros.html"},
{"Name": ["Rahm, Jon"], "Link": "https://www.pgatour.com/players/players/player.46970.jon-rahm.html"},
{"Name": ["Rainaud, Adam"], "Link": "https://www.pgatour.com/players/players/player.46488.adam-rainaud.html"},
{"Name": ["Ramsay, Richie"], "Link": "https://www.pgatour.com/players/players/player.29531.richie-ramsay.html"},
{"Name": ["Randolph, Sam"], "Link": "https://www.pgatour.com/players/players/player.01984.sam-randolph.html"},
{"Name": ["Reavie, Chez"], "Link": "https://www.pgatour.com/players/players/player.26476.chez-reavie.html"},
{"Name": ["Reed, Patrick"], "Link": "https://www.pgatour.com/players/players/player.34360.patrick-reed.html"},
{"Name": ["Reeves, Seth"], "Link": "https://www.pgatour.com/players/players/player.47856.seth-reeves.html"},
{"Name": ["Regalado, Victor"], "Link": "https://www.pgatour.com/players/players/player.01994.victor-regalado.html"},
{"Name": ["Reid, Mike"], "Link": "https://www.pgatour.com/players/players/player.01996.mike-reid.html"},
{"Name": ["Reid, Steve"], "Link": "https://www.pgatour.com/players/players/player.01997.steve-reid.html"},
{"Name": ["Remesy, Jean-Francois"], "Link": "https://www.pgatour.com/players/players/player.24389.jean-francois-remesy.html"},
{"Name": ["Renner, Jack"], "Link": "https://www.pgatour.com/players/players/player.01998.jack-renner.html"},
{"Name": ["Riley, Chris"], "Link": "https://www.pgatour.com/players/players/player.20127.chris-riley.html"},
{"Name": ["Rinker, Larry"], "Link": "https://www.pgatour.com/players/players/player.02007.larry-rinker.html"},
{"Name": ["Roach, Wes"], "Link": "https://www.pgatour.com/players/players/player.35732.wes-roach.html"},
{"Name": ["Roberts, Loren"], "Link": "https://www.pgatour.com/players/players/player.02010.loren-roberts.html"},
{"Name": ["Rock, Robert"], "Link": "https://www.pgatour.com/players/players/player.26539.robert-rock.html"},
{"Name": ["Rodgers, Patrick"], "Link": "https://www.pgatour.com/players/players/player.36699.patrick-rodgers.html"},
{"Name": ["Rodriguez, Chi Chi"], "Link": "https://www.pgatour.com/players/players/player.02015.chi-chi-rodriguez.html"},
{"Name": ["Rodríguez, José de Jesús"], "Link": "https://www.pgatour.com/players/players/player.32058.jose-de-jesus-rodriguez.html"},
{"Name": ["Rogers, Bill"], "Link": "https://www.pgatour.com/players/players/player.02016.bill-rogers.html"},
{"Name": ["Rollins, John"], "Link": "https://www.pgatour.com/players/players/player.22913.john-rollins.html"},
{"Name": ["Romero, Andres"], "Link": "https://www.pgatour.com/players/players/player.25562.andres-romero.html"},
{"Name": ["Rose, Clarence"], "Link": "https://www.pgatour.com/players/players/player.02023.clarence-rose.html"},
{"Name": ["Rose, Justin"], "Link": "https://www.pgatour.com/players/players/player.22405.justin-rose.html"},
{"Name": ["Rummells, Dave"], "Link": "https://www.pgatour.com/players/players/player.02033.dave-rummells.html"},
{"Name": ["Ryder, Sam"], "Link": "https://www.pgatour.com/players/players/player.37275.sam-ryder.html"},
{"Name": ["Sabbatini, Rory"], "Link": "https://www.pgatour.com/players/players/player.23621.rory-sabbatini.html"},
{"Name": ["Sander, Bill"], "Link": "https://www.pgatour.com/players/players/player.02041.bill-sander.html"},
{"Name": ["Sanders, Doug"], "Link": "https://www.pgatour.com/players/players/player.02042.doug-sanders.html"},
{"Name": ["Sarazen, Gene"], "Link": "https://www.pgatour.com/players/players/player.05546.gene-sarazen.html"},
{"Name": ["Sauers, Gene"], "Link": "https://www.pgatour.com/players/players/player.02049.gene-sauers.html"},
{"Name": ["Saunders, Sam"], "Link": "https://www.pgatour.com/players/players/player.29223.sam-saunders.html"},
{"Name": ["Schauffele, Xander"], "Link": "https://www.pgatour.com/players/players/player.48081.xander-schauffele.html"},
{"Name": ["Schenk, Adam"], "Link": "https://www.pgatour.com/players/players/player.47347.adam-schenk.html"},
{"Name": ["Scherrer, Tom"], "Link": "https://www.pgatour.com/players/players/player.10649.tom-scherrer.html"},
{"Name": ["Schnell, Brady"], "Link": "https://www.pgatour.com/players/players/player.30786.brady-schnell.html"},
{"Name": ["Schniederjans, Ollie"], "Link": "https://www.pgatour.com/players/players/player.46501.ollie-schniederjans.html"},
{"Name": ["Schroeder, John"], "Link": "https://www.pgatour.com/players/players/player.02064.john-schroeder.html"},
{"Name": ["Schulz, Ted"], "Link": "https://www.pgatour.com/players/players/player.02067.ted-schulz.html"},
{"Name": ["Schwartzel, Charl"], "Link": "https://www.pgatour.com/players/players/player.26331.charl-schwartzel.html"},
{"Name": ["Scott, Adam"], "Link": "https://www.pgatour.com/players/players/player.24502.adam-scott.html"},
{"Name": ["Senden, John"], "Link": "https://www.pgatour.com/players/players/player.20645.john-senden.html"},
{"Name": ["Sharma, Shubhankar"], "Link": "https://www.pgatour.com/players/players/player.39113.shubhankar-sharma.html"},
{"Name": ["Shaw, Tom"], "Link": "https://www.pgatour.com/players/players/player.02083.tom-shaw.html"},
{"Name": ["Shearer, Bob"], "Link": "https://www.pgatour.com/players/players/player.02084.bob-shearer.html"},
{"Name": ["Shih-chang, Chan"], "Link": "https://www.pgatour.com/players/players/player.29078.chan-shih-chang.html"},
{"Name": ["Short, Jr., Wes"], "Link": "https://www.pgatour.com/players/players/player.07013.wes-short--jr-.html"},
{"Name": ["Sieckmann, Tom"], "Link": "https://www.pgatour.com/players/players/player.02090.tom-sieckmann.html"},
{"Name": ["Siem, Marcel"], "Link": "https://www.pgatour.com/players/players/player.23481.marcel-siem.html"},
{"Name": ["Sifford, Charles"], "Link": "https://www.pgatour.com/players/players/player.02091.charles-sifford.html"},
{"Name": ["Sikes, R.H."], "Link": "https://www.pgatour.com/players/players/player.02093.r-h--sikes.html"},
{"Name": ["Sills, Tony"], "Link": "https://www.pgatour.com/players/players/player.02094.tony-sills.html"},
{"Name": ["Silverman, Ben"], "Link": "https://www.pgatour.com/players/players/player.39327.ben-silverman.html"},
{"Name": ["Simpson, Scott"], "Link": "https://www.pgatour.com/players/players/player.02099.scott-simpson.html"},
{"Name": ["Simpson, Tim"], "Link": "https://www.pgatour.com/players/players/player.02100.tim-simpson.html"},
{"Name": ["Simpson, Webb"], "Link": "https://www.pgatour.com/players/players/player.29221.webb-simpson.html"},
{"Name": ["Sindelar, Joey"], "Link": "https://www.pgatour.com/players/players/player.02101.joey-sindelar.html"},
{"Name": ["Singh, Jeev Milkha"], "Link": "https://www.pgatour.com/players/players/player.20686.jeev-milkha-singh.html"},
{"Name": ["Singh, Vijay"], "Link": "https://www.pgatour.com/players/players/player.06567.vijay-singh.html"},
{"Name": ["Slattery, Lee"], "Link": "https://www.pgatour.com/players/players/player.25321.lee-slattery.html"},
{"Name": ["Sloan, Roger"], "Link": "https://www.pgatour.com/players/players/player.33486.roger-sloan.html"},
{"Name": ["Slocum, Heath"], "Link": "https://www.pgatour.com/players/players/player.22293.heath-slocum.html"},
{"Name": ["Sluman, Jeff"], "Link": "https://www.pgatour.com/players/players/player.02104.jeff-sluman.html"},
{"Name": ["Smith, Bob"], "Link": "https://www.pgatour.com/players/players/player.02105.bob-smith.html"},
{"Name": ["Smith, Cameron"], "Link": "https://www.pgatour.com/players/players/player.35891.cameron-smith.html"},
{"Name": ["Smith, Chris"], "Link": "https://www.pgatour.com/players/players/player.02106.chris-smith.html"},
{"Name": ["Smith, Jordan L"], "Link": "https://www.pgatour.com/players/players/player.46464.jordan-l-smith.html"},
{"Name": ["Snead, J.C."], "Link": "https://www.pgatour.com/players/players/player.02118.j-c--snead.html"},
{"Name": ["Snead, Sam"], "Link": "https://www.pgatour.com/players/players/player.02119.sam-snead.html"},
{"Name": ["Snedeker, Brandt"], "Link": "https://www.pgatour.com/players/players/player.27649.brandt-snedeker.html"},
{"Name": ["Sneed, Ed"], "Link": "https://www.pgatour.com/players/players/player.02120.ed-sneed.html"},
{"Name": ["Snyder, Brent"], "Link": "https://www.pgatour.com/players/players/player.48138.brent-snyder.html"},
{"Name": ["Snyder III, Joey"], "Link": "https://www.pgatour.com/players/players/player.21951.joey-snyder-iii.html"},
{"Name": ["Song, Young-han"], "Link": "https://www.pgatour.com/players/players/player.36521.young-han-song.html"},
{"Name": ["Sowards, Bob"], "Link": "https://www.pgatour.com/players/players/player.12309.bob-sowards.html"},
{"Name": ["Spaun, J.J."], "Link": "https://www.pgatour.com/players/players/player.39324.j-j--spaun.html"},
{"Name": ["Spieth, Jordan"], "Link": "https://www.pgatour.com/players/players/player.34046.jordan-spieth.html"},
{"Name": ["Spray, Steve"], "Link": "https://www.pgatour.com/players/players/player.02130.steve-spray.html"},
{"Name": ["Springer, Mike"], "Link": "https://www.pgatour.com/players/players/player.02131.mike-springer.html"},
{"Name": ["Stadler, Craig"], "Link": "https://www.pgatour.com/players/players/player.02133.craig-stadler.html"},
{"Name": ["Stadler, Kevin"], "Link": "https://www.pgatour.com/players/players/player.26679.kevin-stadler.html"},
{"Name": ["Stal, Gary"], "Link": "https://www.pgatour.com/players/players/player.32493.gary-stal.html"},
{"Name": ["Stallings, Scott"], "Link": "https://www.pgatour.com/players/players/player.30692.scott-stallings.html"},
{"Name": ["Standly, Mike"], "Link": "https://www.pgatour.com/players/players/player.02135.mike-standly.html"},
{"Name": ["Stankowski, Paul"], "Link": "https://www.pgatour.com/players/players/player.08375.paul-stankowski.html"},
{"Name": ["Stanley, Kyle"], "Link": "https://www.pgatour.com/players/players/player.30110.kyle-stanley.html"},
{"Name": ["Steele, Brendan"], "Link": "https://www.pgatour.com/players/players/player.29518.brendan-steele.html"},
{"Name": ["Stefani, Shawn"], "Link": "https://www.pgatour.com/players/players/player.33418.shawn-stefani.html"},
{"Name": ["Stenson, Henrik"], "Link": "https://www.pgatour.com/players/players/player.21528.henrik-stenson.html"},
{"Name": ["Sterne, Richard"], "Link": "https://www.pgatour.com/players/players/player.24459.richard-sterne.html"},
{"Name": ["Stewart, Payne"], "Link": "https://www.pgatour.com/players/players/player.02146.payne-stewart.html"},
{"Name": ["Stockton, Dave"], "Link": "https://www.pgatour.com/players/players/player.02152.dave-stockton.html"},
{"Name": ["Stolz, Andre"], "Link": "https://www.pgatour.com/players/players/player.20580.andre-stolz.html"},
{"Name": ["Stone, Brandon"], "Link": "https://www.pgatour.com/players/players/player.35225.brandon-stone.html"},
{"Name": ["Storm, Graeme"], "Link": "https://www.pgatour.com/players/players/player.23969.graeme-storm.html"},
{"Name": ["Straka, Sepp"], "Link": "https://www.pgatour.com/players/players/player.49960.sepp-straka.html"},
{"Name": ["Strange, Curtis"], "Link": "https://www.pgatour.com/players/players/player.02159.curtis-strange.html"},
{"Name": ["Streb, Robert"], "Link": "https://www.pgatour.com/players/players/player.34431.robert-streb.html"},
{"Name": ["Streck, Ron"], "Link": "https://www.pgatour.com/players/players/player.02160.ron-streck.html"},
{"Name": ["Streelman, Kevin"], "Link": "https://www.pgatour.com/players/players/player.27214.kevin-streelman.html"},
{"Name": ["Stricker, Steve"], "Link": "https://www.pgatour.com/players/players/player.06527.steve-stricker.html"},
{"Name": ["Stroud, Chris"], "Link": "https://www.pgatour.com/players/players/player.27963.chris-stroud.html"},
{"Name": ["Stuard, Brian"], "Link": "https://www.pgatour.com/players/players/player.31560.brian-stuard.html"},
{"Name": ["Sturgeon, Grant"], "Link": "https://www.pgatour.com/players/players/player.33545.grant-sturgeon.html"},
{"Name": ["Sucher, Zack"], "Link": "https://www.pgatour.com/players/players/player.33449.zack-sucher.html"},
{"Name": ["Sullivan, Andy"], "Link": "https://www.pgatour.com/players/players/player.35314.andy-sullivan.html"},
{"Name": ["Sullivan, Mike"], "Link": "https://www.pgatour.com/players/players/player.02167.mike-sullivan.html"},
{"Name": ["Summerhays, Daniel"], "Link": "https://www.pgatour.com/players/players/player.25834.daniel-summerhays.html"},
{"Name": ["Suri, Julian"], "Link": "https://www.pgatour.com/players/players/player.45478.julian-suri.html"},
{"Name": ["Sutherland, Kevin"], "Link": "https://www.pgatour.com/players/players/player.06595.kevin-sutherland.html"},
{"Name": ["Sutton, Hal"], "Link": "https://www.pgatour.com/players/players/player.02170.hal-sutton.html"},
{"Name": ["Svensson, Adam"], "Link": "https://www.pgatour.com/players/players/player.40115.adam-svensson.html"},
{"Name": ["Swafford, Hudson"], "Link": "https://www.pgatour.com/players/players/player.34264.hudson-swafford.html"},
{"Name": ["Taniguchi, Toru"], "Link": "https://www.pgatour.com/players/players/player.20935.toru-taniguchi.html"},
{"Name": ["Tanihara, Hideto"], "Link": "https://www.pgatour.com/players/players/player.21498.hideto-tanihara.html"},
{"Name": ["Tataurangi, Phil"], "Link": "https://www.pgatour.com/players/players/player.12663.phil-tataurangi.html"},
{"Name": ["Taylor, Nick"], "Link": "https://www.pgatour.com/players/players/player.25493.nick-taylor.html"},
{"Name": ["Taylor, Vaughn"], "Link": "https://www.pgatour.com/players/players/player.23325.vaughn-taylor.html"},
{"Name": ["Teater, Josh"], "Link": "https://www.pgatour.com/players/players/player.27330.josh-teater.html"},
{"Name": ["Ten Broeck, Lance"], "Link": "https://www.pgatour.com/players/players/player.02185.lance-ten-broeck.html"},
{"Name": ["Tewell, Doug"], "Link": "https://www.pgatour.com/players/players/player.02190.doug-tewell.html"},
{"Name": ["Thomas, Justin"], "Link": "https://www.pgatour.com/players/players/player.33448.justin-thomas.html"},
{"Name": ["Thompson, Chris"], "Link": "https://www.pgatour.com/players/players/player.10387.chris-thompson.html"},
{"Name": ["Thompson, Leonard"], "Link": "https://www.pgatour.com/players/players/player.02195.leonard-thompson.html"},
{"Name": ["Thompson, Michael"], "Link": "https://www.pgatour.com/players/players/player.32150.michael-thompson.html"},
{"Name": ["Thompson, Rocky"], "Link": "https://www.pgatour.com/players/players/player.02197.rocky-thompson.html"},
{"Name": ["Thomson, Peter"], "Link": "https://www.pgatour.com/players/players/player.02199.peter-thomson.html"},
{"Name": ["Thorpe, Jim"], "Link": "https://www.pgatour.com/players/players/player.02201.jim-thorpe.html"},
{"Name": ["Todd, Brendon"], "Link": "https://www.pgatour.com/players/players/player.30927.brendon-todd.html"},
{"Name": ["Tokimatsu, Ryuko"], "Link": "https://www.pgatour.com/players/players/player.37249.ryuko-tokimatsu.html"},
{"Name": ["Toms, David"], "Link": "https://www.pgatour.com/players/players/player.02206.david-toms.html"},
{"Name": ["Toski, Bob"], "Link": "https://www.pgatour.com/players/players/player.02208.bob-toski.html"},
{"Name": ["Trahan, D.J."], "Link": "https://www.pgatour.com/players/players/player.23788.d-j--trahan.html"},
{"Name": ["Trainer, Martin"], "Link": "https://www.pgatour.com/players/players/player.35617.martin-trainer.html"},
{"Name": ["Trevino, Lee"], "Link": "https://www.pgatour.com/players/players/player.02213.lee-trevino.html"},
{"Name": ["Tringale, Cameron"], "Link": "https://www.pgatour.com/players/players/player.33419.cameron-tringale.html"},
{"Name": ["Triplett, Kirk"], "Link": "https://www.pgatour.com/players/players/player.02214.kirk-triplett.html"},
{"Name": ["Tryba, Ted"], "Link": "https://www.pgatour.com/players/players/player.02218.ted-tryba.html"},
{"Name": ["Turnesa, Marc"], "Link": "https://www.pgatour.com/players/players/player.26668.marc-turnesa.html"},
{"Name": ["Tway, Bob"], "Link": "https://www.pgatour.com/players/players/player.02223.bob-tway.html"},
{"Name": ["Tway, Kevin"], "Link": "https://www.pgatour.com/players/players/player.32333.kevin-tway.html"},
{"Name": ["Twiggs, Greg"], "Link": "https://www.pgatour.com/players/players/player.02224.greg-twiggs.html"},
{"Name": ["Twitty, Howard"], "Link": "https://www.pgatour.com/players/players/player.02225.howard-twitty.html"},
{"Name": ["Uihlein, Peter"], "Link": "https://www.pgatour.com/players/players/player.29484.peter-uihlein.html"},
{"Name": ["Uresti, Omar"], "Link": "https://www.pgatour.com/players/players/player.08385.omar-uresti.html"},
{"Name": ["Utley, Stan"], "Link": "https://www.pgatour.com/players/players/player.02230.stan-utley.html"},
{"Name": ["Van Aswegen, Tyrone"], "Link": "https://www.pgatour.com/players/players/player.28132.tyrone-van-aswegen.html"},
{"Name": ["Van Pelt, Bo"], "Link": "https://www.pgatour.com/players/players/player.23623.bo-van-pelt.html"},
{"Name": ["van Rooyen, Erik"], "Link": "https://www.pgatour.com/players/players/player.40006.erik-van-rooyen.html"},
{"Name": ["Varner III, Harold"], "Link": "https://www.pgatour.com/players/players/player.37189.harold-varner-iii.html"},
{"Name": ["Vegas, Jhonattan"], "Link": "https://www.pgatour.com/players/players/player.27064.jhonattan-vegas.html"},
{"Name": ["Venezio, Daniel"], "Link": "https://www.pgatour.com/players/players/player.48137.daniel-venezio.html"},
{"Name": ["Verplank, Scott"], "Link": "https://www.pgatour.com/players/players/player.02239.scott-verplank.html"},
{"Name": ["Villegas, Camilo"], "Link": "https://www.pgatour.com/players/players/player.27770.camilo-villegas.html"},
{"Name": ["Wadkins, Bobby"], "Link": "https://www.pgatour.com/players/players/player.02241.bobby-wadkins.html"},
{"Name": ["Wadkins, Lanny"], "Link": "https://www.pgatour.com/players/players/player.02242.lanny-wadkins.html"},
{"Name": ["Wadsworth, Fred"], "Link": "https://www.pgatour.com/players/players/player.02244.fred-wadsworth.html"},
{"Name": ["Wagner, Johnson"], "Link": "https://www.pgatour.com/players/players/player.26951.johnson-wagner.html"},
{"Name": ["Waite, Grant"], "Link": "https://www.pgatour.com/players/players/player.02245.grant-waite.html"},
{"Name": ["Waldorf, Duffy"], "Link": "https://www.pgatour.com/players/players/player.02246.duffy-waldorf.html"},
{"Name": ["Walker, Jimmy"], "Link": "https://www.pgatour.com/players/players/player.25632.jimmy-walker.html"},
{"Name": ["Wallace, Matt"], "Link": "https://www.pgatour.com/players/players/player.48887.matt-wallace.html"},
{"Name": ["Warren, Marc"], "Link": "https://www.pgatour.com/players/players/player.25841.marc-warren.html"},
{"Name": ["Watney, Nick"], "Link": "https://www.pgatour.com/players/players/player.27095.nick-watney.html"},
{"Name": ["Watson, Bubba"], "Link": "https://www.pgatour.com/players/players/player.25804.bubba-watson.html"},
{"Name": ["Watson, Denis"], "Link": "https://www.pgatour.com/players/players/player.02255.denis-watson.html"},
{"Name": ["Watson, Tom"], "Link": "https://www.pgatour.com/players/players/player.02256.tom-watson.html"},
{"Name": ["Weaver, Bert"], "Link": "https://www.pgatour.com/players/players/player.02259.bert-weaver.html"},
{"Name": ["Weaver, DeWitt"], "Link": "https://www.pgatour.com/players/players/player.02260.dewitt-weaver.html"},
{"Name": ["Weekley, Boo"], "Link": "https://www.pgatour.com/players/players/player.26289.boo-weekley.html"},
{"Name": ["Weibring, D.A."], "Link": "https://www.pgatour.com/players/players/player.02267.d-a--weibring.html"},
{"Name": ["Weir, Mike"], "Link": "https://www.pgatour.com/players/players/player.10423.mike-weir.html"},
{"Name": ["Weiskopf, Tom"], "Link": "https://www.pgatour.com/players/players/player.02268.tom-weiskopf.html"},
{"Name": ["Werenski, Richy"], "Link": "https://www.pgatour.com/players/players/player.47128.richy-werenski.html"},
{"Name": ["Westwood, Lee"], "Link": "https://www.pgatour.com/players/players/player.20396.lee-westwood.html"},
{"Name": ["Wetterich, Brett"], "Link": "https://www.pgatour.com/players/players/player.23322.brett-wetterich.html"},
{"Name": ["Wi, Charlie"], "Link": "https://www.pgatour.com/players/players/player.20160.charlie-wi.html"},
{"Name": ["Wiebe, Mark"], "Link": "https://www.pgatour.com/players/players/player.02279.mark-wiebe.html"},
{"Name": ["Wiechers, Jim"], "Link": "https://www.pgatour.com/players/players/player.02280.jim-wiechers.html"},
{"Name": ["Wiesberger, Bernd"], "Link": "https://www.pgatour.com/players/players/player.29454.bernd-wiesberger.html"},
{"Name": ["Willett, Danny"], "Link": "https://www.pgatour.com/players/players/player.32139.danny-willett.html"},
{"Name": ["Williams, Lee"], "Link": "https://www.pgatour.com/players/players/player.28310.lee-williams.html"},
{"Name": ["Williamson, Jay"], "Link": "https://www.pgatour.com/players/players/player.10425.jay-williamson.html"},
{"Name": ["Willis, Garrett"], "Link": "https://www.pgatour.com/players/players/player.20436.garrett-willis.html"},
{"Name": ["Wilson, Dean"], "Link": "https://www.pgatour.com/players/players/player.12602.dean-wilson.html"},
{"Name": ["Wilson, Mark"], "Link": "https://www.pgatour.com/players/players/player.21878.mark-wilson.html"},
{"Name": ["Wiratchant, Thaworn"], "Link": "https://www.pgatour.com/players/players/player.22110.thaworn-wiratchant.html"},
{"Name": ["Wise, Aaron"], "Link": "https://www.pgatour.com/players/players/player.49964.aaron-wise.html"},
{"Name": ["Wood, Chris"], "Link": "https://www.pgatour.com/players/players/player.22000.chris-wood.html"},
{"Name": ["Wood, Willie"], "Link": "https://www.pgatour.com/players/players/player.02294.willie-wood.html"},
{"Name": ["Woodland, Gary"], "Link": "https://www.pgatour.com/players/players/player.31323.gary-woodland.html"},
{"Name": ["Woods, Tiger"], "Link": "https://www.pgatour.com/players/players/player.08793.tiger-woods.html"},
{"Name": ["Wright, Chase"], "Link": "https://www.pgatour.com/players/players/player.37340.chase-wright.html"},
{"Name": ["Wright, Michael"], "Link": "https://www.pgatour.com/players/players/player.27024.michael-wright.html"},
{"Name": ["Wu, Ashun"], "Link": "https://www.pgatour.com/players/players/player.33870.ashun-wu.html"},
{"Name": ["Wyatt, Bobby"], "Link": "https://www.pgatour.com/players/players/player.46507.bobby-wyatt.html"},
{"Name": ["Yang, Y.E."], "Link": "https://www.pgatour.com/players/players/player.24663.y-e--yang.html"},
{"Name": ["Young, Steven"], "Link": "https://www.pgatour.com/players/players/player.22746.steven-young.html"},
{"Name": ["Yun, Andrew"], "Link": "https://www.pgatour.com/players/players/player.35544.andrew-yun.html"},
{"Name": ["Zanotti, Fabrizio"], "Link": "https://www.pgatour.com/players/players/player.29939.fabrizio-zanotti.html"},
{"Name": ["Zoeller, Fuzzy"], "Link": "https://www.pgatour.com/players/players/player.02321.fuzzy-zoeller.html"},
{"Name": ["Zokol, Richard"], "Link": "https://www.pgatour.com/players/players/player.02322.richard-zokol.html"}
]